Workbook

Sheet THÁNG 2
A1: STT | B1: MÃ KHÁCH HÀNG | C1: NHÂN VIÊN | D1: KHÁCH HÀNG | E1: CÔNG VIỆC | F1: SỐ TỜ KHAI | G1: LOẠI HÌNH | H1: NGÀY TỜ KHAI | I1: LOẠI HÀNG | J1: LUỒNG TK | K1: HẢI QUAN | L1: C/O | M1: SỐ INV/VAT | N1: SỐ BILL | O1: SỐ BOOKING | P1: SỐ LƯỢNG | T1: (KIỆN, KG) | U1: SỐ CONTAINER | V1: THÔNG BÁO PHÍ CSHT | W1: SỐ TIỀN CSHT | X1: CẢNG XUẤT - CẢNG NHẬP | Y1: GHI CHÚ
P2: 20' | Q2: 40' | R2: LCL | S2: TC
A4: =ROW( ) -3 -> 1 | B4: =VLOOKUP(D4,DSKH!$A:$B,2,0) -> A-17 | C4: KHÁCH | D4: NHỰA RELIABLE | E4: N | F4: 107949987130 | G4: A12 | H4: 46055 | I4: NL | J4: V | K4: BH | L4: E | M4: INVJYSP251231ZKXS-2299 | N4: 260126265212301 | Q4: 5 | U4: MRSU4112026 MSKU1248240 HASU4111143 MRKU5310810 MRSU6565232 | V4: V3PHT202610910717 | W4: 2500000 | X4: CÁT LÁI
A5: =ROW( ) -3 -> 2 | B5: =VLOOKUP(D5,DSKH!$A:$B,2,0) -> A-17 | C5: KHÁCH | D5: NHỰA RELIABLE | E5: N | F5: 107950043610 | G5: A12 | H5: 46055 | I5: NL | J5: V | K5: BH | L5: KV | M5: 9000338290 | N5: SNKO010260102079 | Q5: 8 | U5: HALU5635561 HLHU8300417 HLHU8456945 SEKU4968806 SKHU6419488 SKHU9407109 SKHU9544694 TRHU4761368 | V5: V3PHT202610910771 | W5: 4000000 | X5: CÁT LÁI
A6: =ROW( ) -3 -> 3 | B6: =VLOOKUP(D6,DSKH!$A:$B,2,0) -> A-17 | C6: KHÁCH | D6: NHỰA RELIABLE | E6: N | F6: 107950115230 | G6: A12 | H6: 46055 | I6: NL | J6: X | K6: BH | M6: 9065601030 | N6: 78440202654 | R6: 1 | T6: 10K / 237KG | X6: TCS
A7: =ROW( ) -3 -> 4 | B7: =VLOOKUP(D7,DSKH!$A:$B,2,0) -> A-17 | C7: KHÁCH | D7: NHỰA RELIABLE | E7: N | F7: 107950142860 | G7: A12 | H7: 46055 | I7: NL | J7: X | K7: BH | M7: U2026023 | N7: 16000790381 | R7: 1 | T7: 1K / 218KG | X7: SCSC
A8: =ROW( ) -3 -> 5 | B8: =VLOOKUP(D8,DSKH!$A:$B,2,0) -> A-39 | C8: KHÁCH | D8: TIGER | E8: N | F8: 107949691840 | G8: E31 | H8: 46055 | I8: NL | J8: X | K8: BH | M8: TI002918 | N8: KWSE2601135 | R8: 1 | T8: 9K / 2842KG | V8: V3PHT202610908477 | W8: 42630 | X8: CÁT LÁI
A9: =ROW( ) -3 -> 6 | B9: =VLOOKUP(D9,DSKH!$A:$B,2,0) -> A-39 | C9: KHÁCH | D9: TIGER | E9: N | F9: 107953321120 | G9: E31 | H9: 46083 | I9: NL | J9: X | K9: BH | M9: C50593271-A | N9: YHHY-0100-6010 | R9: 1 | T9: 2K / 13500KG | V9: V3PHT202610918486 | W9: 202500 | X9: TÂN THUẬN
A10: =ROW( ) -3 -> 7 | B10: =VLOOKUP(D10,DSKH!$A:$B,2,0) -> A-56 | C10: KHÁCH | D10: SANYO - TRANCY | E10: X | F10: 308219633060 | G10: E62 | H10: 46083 | I10: NL | J10: X | K10: BH | M10: SVN025-2026 | N10: 122600036909701 | P10: 1 | U10: SKLU2035522 | V10: V3PHT202610918535 | W10: 250000 | X10: CÁT LÁI
A11: =ROW( ) -3 -> 8 | B11: =VLOOKUP(D11,DSKH!$A:$B,2,0) -> A-597 | C11: =IF(AND(D11<>"", F11<>""), "HẢI YẾN", "") -> HẢI YẾN | D11: WHITTIER WOOD | E11: N | F11: 107947484850 | G11: E11 | H11: 46055 | I11: NL | J11: V | K11: CX | M11: 6409 | N11: YMJAW152233710 | Q11: 1 | U11: TGBU6146580 | V11: 263650289166 | W11: 500000 | X11: CAT LAI | Y11: KDTV: BNN2026035043
A12: =ROW( ) -3 -> 9 | B12: =VLOOKUP(D12,DSKH!$A:$B,2,0) -> A-597 | C12: =IF(AND(D12<>"", F12<>""), "HẢI YẾN", "") -> HẢI YẾN | D12: WHITTIER WOOD | E12: N | F12: 107947501760 | G12: E11 | H12: 46055 | I12: NL | J12: X | K12: CX | M12: PO00000161 | N12: 132G500775 | P12: 1 | U12: WHSU2633690 | V12: 202610907733 | W12: 250000 | X12: CAT LAI
A13: =ROW( ) -3 -> 10 | B13: =VLOOKUP(D13,DSKH!$A:$B,2,0) -> A-29 | C13: =IF(AND(D13<>"", F13<>""), "HẢI YẾN", "") -> HẢI YẾN | D13: GIPT - TQVĐ | E13: X | F13: 308214881720 | G13: E62 | H13: 46055 | I13: NL | J13: X | K13: TN | M13: FTM260201 | O13: 26015878 | R13: 1 | T13: 2PP/332.22KG | X13: KHO CAT LAI
A14: =ROW( ) -3 -> 11 | B14: =VLOOKUP(D14,DSKH!$A:$B,2,0) -> A-597 | C14: =IF(AND(D14<>"", F14<>""), "HẢI YẾN", "") -> HẢI YẾN | D14: WHITTIER WOOD | E14: X | F14: 308216093640 | G14: E42 | H14: 46055 | I14: NL | J14: V | K14: CX | M14: 0 5131 | O14: YMJAW490499457 | Q14: 1 | U14: TGBU6764207 | X14: ICD BINH DUONG
A15: =ROW( ) -3 -> 12 | B15: =VLOOKUP(D15,DSKH!$A:$B,2,0) -> A-502 | C15: =IF(AND(D15<>"", F15<>""), "HẢI YẾN", "") -> HẢI YẾN | D15: RYDER | E15: N | F15: 107949907110 | G15: E31 | H15: 46055 | I15: NL | J15: X | K15: DN3 | M15: 980117374 | N15: ONEYSINF79642800 | P15: 1 | U15: ONEU3216535 | V15: 202610910871 | W15: 250000 | X15: CAT LAI
A16: =ROW( ) -3 -> 13 | B16: =VLOOKUP(D16,DSKH!$A:$B,2,0) -> A-502 | C16: =IF(AND(D16<>"", F16<>""), "HẢI YẾN", "") -> HẢI YẾN | D16: RYDER | E16: N | F16: 107949987460 | G16: E31 | H16: 46055 | I16: NL | J16: X | K16: DN3 | M16: 4250423 | N16: 6271255782 | R16: 1 | T16: 1CT/1.5KG | X16: KHO DHL
A17: =ROW( ) -3 -> 14 | B17: =VLOOKUP(D17,DSKH!$A:$B,2,0) -> A-324 | C17: =IF(AND(D17<>"", F17<>""), "HẢI YẾN", "") -> HẢI YẾN | D17: SCHAEFFLER | E17: N | F17: 107951307920 | G17: E31 | H17: 46055 | I17: NL | J17: X | K17: BH | M17: ES0252604300 | N17: AMD49007509 | R17: 1 | T17: 2PK/17.2KG | X17: KHO SCSC
A18: =ROW( ) -3 -> 15 | B18: =VLOOKUP(D18,DSKH!$A:$B,2,0) -> A-324 | C18: =IF(AND(D18<>"", F18<>""), "HẢI YẾN", "") -> HẢI YẾN | D18: SCHAEFFLER | E18: N | F18: 107951309910 | G18: E31 | H18: 46055 | I18: NL | J18: X | K18: BH | M18: 200496/25-26 | N18: DEL10598537 | R18: 1 | T18: 1PP/75KG | X18: KHO TCS
A19: =ROW( ) -3 -> 16 | B19: =VLOOKUP(D19,DSKH!$A:$B,2,0) -> A-324 | C19: =IF(AND(D19<>"", F19<>""), "HẢI YẾN", "") -> HẢI YẾN | D19: SCHAEFFLER | E19: N | F19: 107951319600 | G19: A12 | H19: 46055 | I19: NL | J19: X | K19: BH | M19: VT260129B | N19: 260100406SGN | R19: 1 | T19: 1PK/288KG | X19: KHO SCSC | Y19: CHUNG LÔ
A20: =ROW( ) -3 -> 17 | B20: =VLOOKUP(D20,DSKH!$A:$B,2,0) -> A-324 | C20: =IF(AND(D20<>"", F20<>""), "HẢI YẾN", "") -> HẢI YẾN | D20: SCHAEFFLER | E20: N | F20: 107951315030 | G20: E31 | H20: 46055 | I20: NL | J20: X | K20: BH | M20: VT260129
A21: =ROW( ) -3 -> 18 | B21: =VLOOKUP(D21,DSKH!$A:$B,2,0) -> A-324 | C21: =IF(AND(D21<>"", F21<>""), "HẢI YẾN", "") -> HẢI YẾN | D21: SCHAEFFLER | E21: N | F21: 107951405920 | G21: A12 | H21: 46055 | I21: NL | J21: X | K21: BH | M21: INAQ260112 | N21: 260100436SGN | R21: 1 | T21: 1PK/38KG | X21: KHO TCS
A22: =ROW( ) -3 -> 19 | B22: =VLOOKUP(D22,DSKH!$A:$B,2,0) -> A-324 | C22: =IF(AND(D22<>"", F22<>""), "HẢI YẾN", "") -> HẢI YẾN | D22: SCHAEFFLER | E22: N | F22: 107952250560 | G22: A41 | H22: 46055 | I22: NL | J22: X | K22: BH | M22: 124734948 | N22: I267505 | R22: 1 | T22: 1CT/54KG | X22: KHO TCS
A23: =ROW( ) -3 -> 20 | B23: =VLOOKUP(D23,DSKH!$A:$B,2,0) -> A-29 | C23: =IF(AND(D23<>"", F23<>""), "HẢI YẾN", "") -> HẢI YẾN | D23: GIPT - TQVĐ | E23: X | F23: 308218160740 | G23: E62 | H23: 46055 | I23: NL | J23: X | K23: TN | M23: R260201 | O23: 2166029340 | Q23: 1 | U23: OOCU7184019 | X23: CÁI MÉP THỊ VẢI
A24: =ROW( ) -3 -> 21 | B24: =VLOOKUP(D24,DSKH!$A:$B,2,0) -> A-324 | C24: =IF(AND(D24<>"", F24<>""), "HẢI YẾN", "") -> HẢI YẾN | D24: SCHAEFFLER | E24: N | F24: 107953064000 | G24: A12 | H24: 46056 | I24: NL | J24: X | K24: BH | M24: UI2526EXP00242 | N24: BOM20552930 | R24: 1 | T24: 1PK/36KG | X24: KHO SCSC
A25: =ROW( ) -3 -> 22 | B25: =VLOOKUP(D25,DSKH!$A:$B,2,0) -> A-502 | C25: =IF(AND(D25<>"", F25<>""), "HẢI YẾN", "") -> HẢI YẾN | D25: RYDER | E25: N | F25: 107953137460 | G25: E31 | H25: 46056 | I25: NL | J25: X | K25: DN3 | M25: 4251821 | N25: 5014370082 | R25: 1 | T25: 1CT/1.6KG | X25: KHO DHL
A26: =ROW( ) -3 -> 23 | B26: =VLOOKUP(D26,DSKH!$A:$B,2,0) -> A-502 | C26: =IF(AND(D26<>"", F26<>""), "HẢI YẾN", "") -> HẢI YẾN | D26: RYDER | E26: N | F26: 107953514430 | G26: H11 | H26: 46056 | I26: NL | J26: V | K26: DN3 | M26: S26012901-280-PMD | N26: 1Z4WF3636795284280 | R26: 1 | T26: 2CT/7.5KG | X26: KHO UPS
A27: =ROW( ) -3 -> 24 | B27: =VLOOKUP(D27,DSKH!$A:$B,2,0) -> A-502 | C27: =IF(AND(D27<>"", F27<>""), "HẢI YẾN", "") -> HẢI YẾN | D27: RYDER | E27: X | F27: 308219721260 | G27: E62 | H27: 46056 | I27: NL | J27: X | K27: DN3 | M27: RD260203-KING-CA | R27: 1 | T27: 10CT/62,2KG | X27: KHO DHL
A28: =ROW( ) -3 -> 25 | B28: =VLOOKUP(D28,DSKH!$A:$B,2,0) -> A-502 | C28: =IF(AND(D28<>"", F28<>""), "HẢI YẾN", "") -> HẢI YẾN | D28: RYDER | E28: X | F28: 308220523460 | G28: E62 | H28: 46056 | I28: NL | J28: V | K28: DN3 | M28: RD260203-SIL-NO | R28: 1 | T28: 1CT/0,8KG | X28: KHO FEDEX
A29: =ROW( ) -3 -> 26 | B29: =VLOOKUP(D29,DSKH!$A:$B,2,0) -> A-502 | C29: =IF(AND(D29<>"", F29<>""), "HẢI YẾN", "") -> HẢI YẾN | D29: RYDER | E29: X | F29: 308220570950 | G29: E62 | H29: 46056 | I29: NL | J29: V | K29: DN3 | M29: RD260203-SIL-AU | R29: 1 | T29: 1CT/1,5KG | X29: KHO DHL
A30: =ROW( ) -3 -> 27 | B30: =VLOOKUP(D30,DSKH!$A:$B,2,0) -> A-597 | C30: =IF(AND(D30<>"", F30<>""), "HẢI YẾN", "") -> HẢI YẾN | D30: WHITTIER WOOD | E30: X | F30: 308220855300 | G30: E42 | H30: 46056 | I30: NL | J30: V | K30: CX | M30: 0 5132 | O30: YMJAW490498992 | Q30: 1 | U30: YMMU6192084 | V30: 264826741762 | W30: 500000 | X30: SOTRANS ICD
A31: =ROW( ) -3 -> 28 | B31: =VLOOKUP(D31,DSKH!$A:$B,2,0) -> A-596 | C31: =IF(AND(D31<>"", F31<>""), "HẢI YẾN", "") -> HẢI YẾN | D31: LEADERSHIP | E31: N | F31: 107953716030 | G31: E15 | H31: 46056 | I31: NL | J31: X | K31: TN | M31: 43 | S31: 1 | T31: 48PK/455.04KG
A32: =ROW( ) -3 -> 29 | B32: =VLOOKUP(D32,DSKH!$A:$B,2,0) -> A-37 | C32: =IF(AND(D32<>"", F32<>""), "HOÀI", "") -> HOÀI | D32: FLEMING | E32: X | F32: 308215019950 | G32: E42 | H32: 46055 | I32: NL | J32: X | K32: CX | M32: PB-2511083 | R32: 1 | T32: 3K/ 18.48KG/0,07CBM | X32: DAMCO
A33: =ROW( ) -3 -> 30 | B33: =VLOOKUP(D33,DSKH!$A:$B,2,0) -> A-37 | C33: =IF(AND(D33<>"", F33<>""), "HOÀI", "") -> HOÀI | D33: FLEMING | E33: X | F33: 308219165940 | G33: E42 | H33: 46056 | I33: NL | J33: X | K33: CX | M33: PB-2511031/2511032 | R33: 1 | T33: 51K/ 314.16KG/1,26CBM | X33: DAMCO
A34: =ROW( ) -3 -> 31 | B34: =VLOOKUP(D34,DSKH!$A:$B,2,0) -> A-37 | C34: =IF(AND(D34<>"", F34<>""), "HOÀI", "") -> HOÀI | D34: FLEMING | E34: X | F34: 308219141330 | G34: E42 | H34: 46056 | I34: NL | J34: X | K34: CX | M34: PB-2511033 | R34: 1 | T34: 126K/ 776.16KG/3,12CBM | X34: DAMCO
A35: =ROW( ) -3 -> 32 | B35: =VLOOKUP(D35,DSKH!$A:$B,2,0) -> A-37 | C35: =IF(AND(D35<>"", F35<>""), "HOÀI", "") -> HOÀI | D35: FLEMING | E35: X | F35: 308215055800 | G35: E42 | H35: 46055 | I35: NL | J35: X | K35: CX | M35: HSH-2508148/2 | R35: 1 | T35: 540K/ 7338.6KG/27,027CBM | X35: TBS
A36: =ROW( ) -3 -> 33 | B36: =VLOOKUP(D36,DSKH!$A:$B,2,0) -> A-298 | C36: =IF(AND(D36<>"", F36<>""), "THẢO", "") -> THẢO | D36: WANHUA | E36: =IF(LEFT(F36,1)="1","N","X") -> N | F36: 107950751160 | G36: A41 | H36: 46055 | I36: NL | J36: V | K36: CNC | M36: SG4056501VN | N36: 263845486 | P36: 2 | T36: 160K/43.720KG | U36: MSKU5602829 TRHU1558038 | X36: TC NHON TRACH | Y36: 0317794954QZH0004694
A37: =ROW( ) -3 -> 34 | B37: =VLOOKUP(D37,DSKH!$A:$B,2,0) -> A-502 | C37: =IF(AND(D37<>"", F37<>""), "THẢO", "") -> THẢO | D37: RYDER | E37: =IF(LEFT(F37,1)="1","N","X") -> N | F37: 107949619630 | G37: E31 | H37: 46055 | I37: NL | J37: X | K37: DN3 | M37: 4250492 | N37: 6271256003 | R37: 1 | T37: 1K/1,6KG | X37: DHL
A38: =ROW( ) -3 -> 35 | B38: =VLOOKUP(D38,DSKH!$A:$B,2,0) -> A-502 | C38: =IF(AND(D38<>"", F38<>""), "THẢO", "") -> THẢO | D38: RYDER | E38: =IF(LEFT(F38,1)="1","N","X") -> N | F38: 107950099130 | G38: A12 | H38: 46055 | I38: NL | J38: X | K38: DN3 | M38: VN260130XF-FEDEX-N | N38: 412669257903 | R38: 1 | T38: 1K/2,6KG | X38: FEDEX
A39: =ROW( ) -3 -> 36 | B39: =VLOOKUP(D39,DSKH!$A:$B,2,0) -> A-502 | C39: =IF(AND(D39<>"", F39<>""), "THẢO", "") -> THẢO | D39: RYDER | E39: =IF(LEFT(F39,1)="1","N","X") -> X | F39: 308211366760 | G39: E52 | H39: 46055 | I39: NL | J39: X | K39: DN3 | M39: RD260203GC09-BOA-VNGC | R39: 1 | T39: 2K/645,21KG | X39: KNQ LF LOGISTICS
A40: =ROW( ) -3 -> 37 | B40: =VLOOKUP(D40,DSKH!$A:$B,2,0) -> A-502 | C40: =IF(AND(D40<>"", F40<>""), "THẢO", "") -> THẢO | D40: RYDER | E40: =IF(LEFT(F40,1)="1","N","X") -> X | F40: 308215724410 | G40: E62 | H40: 46055 | I40: NL | J40: X | K40: DN3 | M40: RD260203-BOA-VN | R40: 1 | T40: 2K/942,6KG | X40: KNQ LF LOGISTICS
A41: =ROW( ) -3 -> 38 | B41: =VLOOKUP(D41,DSKH!$A:$B,2,0) -> A-213 | C41: =IF(AND(D41<>"", F41<>""), "THẢO", "") -> THẢO | D41: REGENT | E41: =IF(LEFT(F41,1)="1","N","X") -> N | F41: 107944743061 | G41: A12 | H41: 46055 | I41: NL | J41: Đ | K41: NT | L41: E | M41: 20260112003 | N41: CKCOSH2521959UWS | P41: 1 | T41: 227K/26.589,1KG | U41: BEAU2587928 | X41: CAT LAI
A42: =ROW( ) -3 -> 39 | B42: =VLOOKUP(D42,DSKH!$A:$B,2,0) -> A-213 | C42: =IF(AND(D42<>"", F42<>""), "THẢO", "") -> THẢO | D42: REGENT | E42: =IF(LEFT(F42,1)="1","N","X") -> N | F42: 107949026510 | G42: A12 | H42: 46055 | I42: NL | J42: V | K42: NT | L42: E | M42: 20260122001 | N42: MEDUYL253745 | P42: 1 | T42: 128K/26.228,5KG | U42: MSBU3256684 | V42: 202610922786 | W42: 250000 | X42: SP-ITC
A43: =ROW( ) -3 -> 40 | B43: =VLOOKUP(D43,DSKH!$A:$B,2,0) -> A-556 | C43: =IF(AND(D43<>"", F43<>""), "THẢO", "") -> THẢO | D43: V.L.I | E43: =IF(LEFT(F43,1)="1","N","X") -> N | F43: 107951681610 | G43: E21 | H43: 46055 | I43: NL | J43: X | K43: BH | M43: VLI-HD55-26005 | S43: 1 | T43: 1.386K/11.978KG
A44: =ROW( ) -3 -> 41 | B44: =VLOOKUP(D44,DSKH!$A:$B,2,0) -> A-564 | C44: =IF(AND(D44<>"", F44<>""), "THẢO", "") -> THẢO | D44: PHOENIX | E44: =IF(LEFT(F44,1)="1","N","X") -> X | F44: 308216420210 | G44: E62 | H44: 46055 | I44: NL | J44: X | K44: TN | M44: 00000017 | S44: 1 | T44: 8K/5.024KG
A45: =ROW( ) -3 -> 42 | B45: =VLOOKUP(D45,DSKH!$A:$B,2,0) -> A-564 | C45: =IF(AND(D45<>"", F45<>""), "THẢO", "") -> THẢO | D45: PHOENIX | E45: =IF(LEFT(F45,1)="1","N","X") -> X | F45: 308216641960 | G45: E62 | H45: 46055 | I45: NL | J45: X | K45: TN | M45: 00000018 | S45: 1 | T45: 16K/10.268KG
A46: =ROW( ) -3 -> 43 | B46: =VLOOKUP(D46,DSKH!$A:$B,2,0) -> A-12 | C46: =IF(AND(D46<>"", F46<>""), "THANH", "") -> THANH | D46: MATSUYA | E46: =IF(LEFT(F46,1)="1","N","X") -> N | F46: 107949742940 | G46: E11 | H46: 46055 | I46: NL | J46: X | K46: TN | M46: K20260128-02 | N46: 8704172050 | R46: 1 | T46: 5k/79,5kg | V46: 0 | X46: DHL
A47: =ROW( ) -3 -> 44 | B47: =VLOOKUP(D47,DSKH!$A:$B,2,0) -> A-12 | C47: =IF(AND(D47<>"", F47<>""), "THANH", "") -> THANH | D47: MATSUYA | E47: =IF(LEFT(F47,1)="1","N","X") -> N | F47: 107949801300 | G47: E11 | H47: 46055 | I47: NL | J47: X | K47: TN | M47: SFQ-3199 | N47: RDCBSGN2601068 | Q47: 1 | U47: SKHU6436994 | V47: 202610908748 | W47: 500000 | X47: CÁT LÁI
A48: =ROW( ) -3 -> 45 | B48: =VLOOKUP(D48,DSKH!$A:$B,2,0) -> A-554 | C48: =IF(AND(D48<>"", F48<>""), "THANH", "") -> THANH | D48: MATSUYA/HEADWAY | E48: =IF(LEFT(F48,1)="1","N","X") -> N | F48: 107949878260 | G48: E11 | H48: 46055 | I48: NL | J48: X | K48: TN | M48: GR-90437 | N48: TYSC022586 | Q48: 3 | U48: ONEU6108576 ONEU7522301 ONEU5553448 | V48: 202610908732 | W48: 1500000 | X48: CÁT LÁI | Y48: tk chung cont
A49: =ROW( ) -3 -> 46 | B49: =VLOOKUP(D49,DSKH!$A:$B,2,0) -> A-554 | C49: =IF(AND(D49<>"", F49<>""), "THANH", "") -> THANH | D49: MATSUYA/HEADWAY | E49: =IF(LEFT(F49,1)="1","N","X") -> N | F49: 107949857850 | G49: E11 | H49: 46055 | I49: NL | J49: V | K49: TN
A50: =ROW( ) -3 -> 47 | B50: =VLOOKUP(D50,DSKH!$A:$B,2,0) -> A-12 | C50: =IF(AND(D50<>"", F50<>""), "THANH", "") -> THANH | D50: MATSUYA | E50: =IF(LEFT(F50,1)="1","N","X") -> X | F50: 308216137300 | G50: E42 | H50: 46055 | I50: NL | J50: X | K50: TN | M50: TK20260202 | R50: 1 | T50: 2k/35kg | V50: 0 | X50: TCS
A51: =ROW( ) -3 -> 48 | B51: =VLOOKUP(D51,DSKH!$A:$B,2,0) -> A-12 | C51: =IF(AND(D51<>"", F51<>""), "THANH", "") -> THANH | D51: MATSUYA | E51: =IF(LEFT(F51,1)="1","N","X") -> X | F51: 308216849050 | G51: B11 | H51: 46055 | I51: NL | J51: X | K51: TN | M51: 65 | S51: 1 | T51: 1k/1,443kg | V51: 0
A52: =ROW( ) -3 -> 49 | B52: =VLOOKUP(D52,DSKH!$A:$B,2,0) -> A-37 | C52: =IF(AND(D52<>"", F52<>""), "THANH", "") -> THANH | D52: FLEMING | E52: =IF(LEFT(F52,1)="1","N","X") -> X | F52: 308216922330 | G52: E42 | H52: 46055 | I52: NL | J52: X | K52: CX | M52: TG-10001622707/ 7 | Q52: 1 | T52: 7418k/19.648,56kg/51.845 | U52: BMOU9863494 | X52: PHÚC LONG
A53: =ROW( ) -3 -> 50 | B53: =VLOOKUP(D53,DSKH!$A:$B,2,0) -> A-37 | C53: =IF(AND(D53<>"", F53<>""), "THANH", "") -> THANH | D53: FLEMING | E53: =IF(LEFT(F53,1)="1","N","X") -> X | F53: 308216988500 | G53: E42 | H53: 46055 | I53: NL | J53: X | K53: CX | M53: TG-10001622707/ 8 | Q53: 1 | T53: 4420k/19,475.34kg/47.481 | U53: SEGU9846750 | X53: PHÚC LONG
A54: =ROW( ) -3 -> 51 | B54: =VLOOKUP(D54,DSKH!$A:$B,2,0) -> A-324 | C54: =IF(AND(D54<>"", F54<>""), "THANH", "") -> THANH | D54: SCHAEFFLER | E54: =IF(LEFT(F54,1)="1","N","X") -> N | F54: 107951158560 | G54: E31 | H54: 46055 | I54: NL | J54: X | K54: BH | M54: 2K26012001V | N54: RAF0152870 | R54: 1 | T54: 14k/396,6kg | V54: 0 | X54: kho cat lai
A55: =ROW( ) -3 -> 52 | B55: =VLOOKUP(D55,DSKH!$A:$B,2,0) -> A-324 | C55: =IF(AND(D55<>"", F55<>""), "THANH", "") -> THANH | D55: SCHAEFFLER | E55: =IF(LEFT(F55,1)="1","N","X") -> N | F55: 107951212500 | G55: A41 | H55: 46055 | I55: NL | J55: V | K55: BH | L55: KV | M55: SCHAEFFLER KOREA-005/26/A41 | N55: SEL0530663 | R55: 1 | T55: 4k/625,2kfg | V55: 0 | X55: kho cat lai
A56: =ROW( ) -3 -> 53 | B56: =VLOOKUP(D56,DSKH!$A:$B,2,0) -> A-37 | C56: =IF(AND(D56<>"", F56<>""), "THANH", "") -> THANH | D56: FLEMING | E56: =IF(LEFT(F56,1)="1","N","X") -> X | F56: 308218138120 | G56: E42 | H56: 46055 | I56: NL | J56: X | K56: CX | M56: AH-2507033 | R56: 1 | T56: 1323k/8,473.86kg/18.838 | X56: CFS KHO 6
A57: =ROW( ) -3 -> 54 | B57: =VLOOKUP(D57,DSKH!$A:$B,2,0) -> A-324 | C57: =IF(AND(D57<>"", F57<>""), "THANH", "") -> THANH | D57: SCHAEFFLER | E57: =IF(LEFT(F57,1)="1","N","X") -> N | F57: 107952197730 | G57: E31 | H57: 46055 | I57: NL | J57: X | K57: BH | M57: 1471532150 | N57: 14630142447 | R57: 1 | T57: 1k/396kg | V57: 0 | X57: kho cat lai
A58: =ROW( ) -3 -> 55 | B58: =VLOOKUP(D58,DSKH!$A:$B,2,0) -> A-37 | C58: =IF(AND(D58<>"", F58<>""), "THANH", "") -> THANH | D58: FLEMING | E58: KBS | F58: 308216922330 | G58: E42 | H58: 46055 | I58: NL | J58: X | K58: CX | U58: BMOU9863494 | V58: 0 | Y58: KBS số cont
A59: =ROW( ) -3 -> 56 | B59: =VLOOKUP(D59,DSKH!$A:$B,2,0) -> A-37 | C59: =IF(AND(D59<>"", F59<>""), "THANH", "") -> THANH | D59: FLEMING | E59: KBS | F59: 308216988500 | G59: E42 | H59: 46055 | I59: NL | J59: X | K59: CX | U59: SEGU9846750 | V59: 0 | Y59: KBS số cont
A60: =ROW( ) -3 -> 57 | B60: =VLOOKUP(D60,DSKH!$A:$B,2,0) -> A-324 | C60: =IF(AND(D60<>"", F60<>""), "THANH", "") -> THANH | D60: SCHAEFFLER | E60: =IF(LEFT(F60,1)="1","N","X") -> X | F60: 308219284610 | G60: E62 | H60: 46083 | I60: NL | J60: X | K60: BH | M60: 6603061767+6603061770 | R60: 1 | T60: 14k/1.784kg | X60: kho cat lai
A61: =ROW( ) -3 -> 58 | B61: =VLOOKUP(D61,DSKH!$A:$B,2,0) -> A-324 | C61: =IF(AND(D61<>"", F61<>""), "THANH", "") -> THANH | D61: SCHAEFFLER | E61: =IF(LEFT(F61,1)="1","N","X") -> X | F61: 308219313640 | G61: E62 | H61: 46083 | I61: NL | J61: X | K61: BH | M61: 6603061769+6603061772 | R61: 1 | T61: 13k/1.566kg | X61: kho cat lai
A62: =ROW( ) -3 -> 59 | B62: =VLOOKUP(D62,DSKH!$A:$B,2,0) -> A-324 | C62: =IF(AND(D62<>"", F62<>""), "THANH", "") -> THANH | D62: SCHAEFFLER | E62: =IF(LEFT(F62,1)="1","N","X") -> X | F62: 308219472100 | G62: E62 | H62: 46083 | I62: NL | J62: X | K62: BH | M62: 6603061778+6603061779+6603061782 | R62: 1 | T62: 26k/4.416kg | X62: kho cat lai
A63: =ROW( ) -3 -> 60 | B63: =VLOOKUP(D63,DSKH!$A:$B,2,0) -> A-324 | C63: =IF(AND(D63<>"", F63<>""), "THANH", "") -> THANH | D63: SCHAEFFLER | E63: =IF(LEFT(F63,1)="1","N","X") -> N | F63: 107953691420 | G63: E31 | H63: 46083 | I63: NL | J63: X | K63: BH | M63: DURASIV-002/26/E31 | R63: 1 | T63: 4k/525kg | V63: 0 | X63: KNQ
A64: =ROW( ) -3 -> 61 | B64: =VLOOKUP(D64,DSKH!$A:$B,2,0) -> A-12 | C64: =IF(AND(D64<>"", F64<>""), "THANH", "") -> THANH | D64: MATSUYA | E64: =IF(LEFT(F64,1)="1","N","X") -> X | F64: 308219822430 | G64: E42 | H64: 46083 | I64: NL | J64: V | K64: TN | M64: MRDSASKR-26008 | P64: 1 | Q64: 1 | U64: SEGU3273100 KMTU9414714 | X64: CÁT LÁI | Y64: ko vận chuyển
A65: =ROW( ) -3 -> 62 | B65: =VLOOKUP(D65,DSKH!$A:$B,2,0) -> A-324 | C65: =IF(AND(D65<>"", F65<>""), "THANH", "") -> THANH | D65: SCHAEFFLER | E65: =IF(LEFT(F65,1)="1","N","X") -> N | F65: 107954404460 | G65: A41 | H65: 46083 | I65: BCL | J65: V | K65: BH | M65: STG-155/25/A41 | N65: 16122514630143058 | Q65: 1 | U65: TCLU5776459 | V65: 0 | X65: cai mep | Y65: tk chung cont
A66: =ROW( ) -3 -> 63 | B66: =VLOOKUP(D66,DSKH!$A:$B,2,0) -> A-324 | C66: =IF(AND(D66<>"", F66<>""), "THANH", "") -> THANH | D66: SCHAEFFLER | E66: =IF(LEFT(F66,1)="1","N","X") -> N | F66: 107954401550 | G66: E31 | H66: 46083 | I66: BCL | J66: X | K66: BH | M66: 137335676 | N66: 16122514630143058 | V66: 0
A67: =ROW( ) -3 -> 64 | B67: =VLOOKUP(D67,DSKH!$A:$B,2,0) -> A-324 | C67: =IF(AND(D67<>"", F67<>""), "THANH", "") -> THANH | D67: SCHAEFFLER | E67: =IF(LEFT(F67,1)="1","N","X") -> N | F67: 107954509240 | G67: E31 | H67: 46083 | I67: BCL | J67: X | K67: BH | M67: 137347841 | N67: 16122514630143568 | V67: 0
A68: =ROW( ) -3 -> 65 | B68: =VLOOKUP(D68,DSKH!$A:$B,2,0) -> A-324 | C68: =IF(AND(D68<>"", F68<>""), "THANH", "") -> THANH | D68: SCHAEFFLER | E68: =IF(LEFT(F68,1)="1","N","X") -> N | F68: 107954551720 | G68: E31 | H68: 46083 | I68: BCL | J68: X | K68: BH | M68: ERNST-028/25/E31 | N68: 16122514630143057 | V68: 0
A69: =ROW( ) -3 -> 66 | B69: =VLOOKUP(D69,DSKH!$A:$B,2,0) -> A-324 | C69: =IF(AND(D69<>"", F69<>""), "THANH", "") -> THANH | D69: SCHAEFFLER | E69: =IF(LEFT(F69,1)="1","N","X") -> N | F69: 107954368910 | G69: E31 | H69: 46083 | I69: BCL | J69: X | K69: BH | M69: RE25-1084 | N69: 16122514630143056 | V69: 0
A70: =ROW( ) -3 -> 67 | B70: =VLOOKUP(D70,DSKH!$A:$B,2,0) -> A-324 | C70: =IF(AND(D70<>"", F70<>""), "THANH", "") -> THANH | D70: SCHAEFFLER | E70: =IF(LEFT(F70,1)="1","N","X") -> N | F70: 107954302630 | G70: A12 | H70: 46083 | I70: BCL | J70: V | K70: BH | L70: REX | M70: IX25/000031 | N70: 16122514630143055 | V70: 0
A71: =ROW( ) -3 -> 68 | B71: =VLOOKUP(D71,DSKH!$A:$B,2,0) -> A-324 | C71: =IF(AND(D71<>"", F71<>""), "THANH", "") -> THANH | D71: SCHAEFFLER | E71: =IF(LEFT(F71,1)="1","N","X") -> N | F71: 107954208460 | G71: A12 | H71: 46083 | I71: BCL | J71: V | K71: BH | L71: REX | M71: 4092141 | N71: 16122514630143054 | V71: 0
A72: =ROW( ) -3 -> 69 | B72: =VLOOKUP(D72,DSKH!$A:$B,2,0) -> A-324 | C72: =IF(AND(D72<>"", F72<>""), "THANH", "") -> THANH | D72: SCHAEFFLER | E72: =IF(LEFT(F72,1)="1","N","X") -> N | F72: 107954099260 | G72: E31 | H72: 46083 | I72: BCL | J72: X | K72: BH | M72: 14001464 | N72: 16122514630143053 | V72: 0
A73: =ROW( ) -3 -> 70 | B73: =VLOOKUP(D73,DSKH!$A:$B,2,0) -> A-324 | C73: =IF(AND(D73<>"", F73<>""), "THANH", "") -> THANH | D73: SCHAEFFLER | E73: =IF(LEFT(F73,1)="1","N","X") -> N | F73: 107954066400 | G73: E31 | H73: 46083 | I73: BCL | J73: X | K73: BH | M73: 2560232171 | N73: 16122514630143052 | V73: 0
A74: =ROW( ) -3 -> 71 | B74: =VLOOKUP(D74,DSKH!$A:$B,2,0) -> A-324 | C74: =IF(AND(D74<>"", F74<>""), "THANH", "") -> THANH | D74: SCHAEFFLER | E74: =IF(LEFT(F74,1)="1","N","X") -> N | F74: 107953988660 | G74: H11 | H74: 46083 | I74: BCL | J74: X | K74: BH | M74: R-251106 | N74: 16122514630143051 | V74: 0
A75: =ROW( ) -3 -> 72 | B75: =VLOOKUP(D75,DSKH!$A:$B,2,0) -> A-56 | C75: DIỆU | D75: HOKURIKU - TRANCY | E75: C/O | F75: 308190444720 | L75: VN-JP 26/04/000425 | Y75: LÀM C/O
A76: =ROW( ) -3 -> 73 | B76: =VLOOKUP(D76,DSKH!$A:$B,2,0) -> A-212 | C76: =IF(AND(D76<>"", F76<>""), "DIỆU", "") -> DIỆU | D76: LEADER | E76: =IF(LEFT(F76,1)="1","N","X") -> N | F76: 107955843920 | G76: E13 | H76: 46083 | I76: NL | J76: X | K76: TN | M76: 00000349 | S76: 1
A77: =ROW( ) -3 -> 74 | B77: =VLOOKUP(D77,DSKH!$A:$B,2,0) -> A-212 | C77: =IF(AND(D77<>"", F77<>""), "DIỆU", "") -> DIỆU | D77: LEADER | E77: =IF(LEFT(F77,1)="1","N","X") -> N | F77: 107954519040 | G77: E13 | H77: 46083 | I77: NL | J77: X | K77: TN | M77: 156 | S77: 1
A78: =ROW( ) -3 -> 75 | B78: =VLOOKUP(D78,DSKH!$A:$B,2,0) -> A-212 | C78: =IF(AND(D78<>"", F78<>""), "DIỆU", "") -> DIỆU | D78: LEADER | E78: =IF(LEFT(F78,1)="1","N","X") -> N | F78: 107954469560 | G78: E13 | H78: 46083 | I78: NL | J78: V | K78: TN | M78: 1 | S78: 1
A79: =ROW( ) -3 -> 76 | B79: =VLOOKUP(D79,DSKH!$A:$B,2,0) -> A-212 | C79: =IF(AND(D79<>"", F79<>""), "DIỆU", "") -> DIỆU | D79: LEADER | E79: =IF(LEFT(F79,1)="1","N","X") -> N | F79: 107953197220 | G79: E15 | H79: 46083 | I79: NL | J79: X | K79: TN | M79: 44 | S79: 1
A80: =ROW( ) -3 -> 77 | B80: =VLOOKUP(D80,DSKH!$A:$B,2,0) -> A-212 | C80: =IF(AND(D80<>"", F80<>""), "DIỆU", "") -> DIỆU | D80: LEADER | E80: =IF(LEFT(F80,1)="1","N","X") -> N | F80: 107951298600 | G80: E13 | H80: 46055 | I80: NL | J80: X | K80: TN | M80: 00000018 | S80: 1
A81: =ROW( ) -3 -> 78 | B81: =VLOOKUP(D81,DSKH!$A:$B,2,0) -> A-212 | C81: =IF(AND(D81<>"", F81<>""), "DIỆU", "") -> DIỆU | D81: LEADER | E81: =IF(LEFT(F81,1)="1","N","X") -> N | F81: 107953424610 | G81: E11 | H81: 46083 | I81: NL | J81: X | K81: TN | M81: FJYN0591 | N81: 11202442952 | R81: 1 | T81: 103 PK / 505 KG | X81: TCS
A82: =ROW( ) -3 -> 79 | B82: =VLOOKUP(D82,DSKH!$A:$B,2,0) -> A-519 | C82: =IF(AND(D82<>"", F82<>""), "DIỆU", "") -> DIỆU | D82: TONG HONG | E82: =IF(LEFT(F82,1)="1","N","X") -> N | F82: 107949742460 | G82: E21 | H82: 46055 | I82: NL | J82: X | K82: NT | M82: FM20260119-01 | N82: RPDSGN2601110 | R82: 1 | T82: 6 PP / 3596.37 KG | V82: 202610908413 | W82: 53946 | X82: CFS CÁT LÁI
A83: =ROW( ) -3 -> 80 | B83: =VLOOKUP(D83,DSKH!$A:$B,2,0) -> A-29 | C83: =IF(AND(D83<>"", F83<>""), "DIỆU", "") -> DIỆU | D83: DELTA-TQVĐ | E83: =IF(LEFT(F83,1)="1","N","X") -> X | F83: 308221060840 | G83: B11 | H83: 46083 | I83: NL | J83: V | K83: TN | M83: 35DW-SSC/26 | O83: 265598616 | Q83: 1 | U83: TCKU7644916 | X83: ĐỒNG NAI
A84: =ROW( ) -3 -> 81 | B84: =VLOOKUP(D84,DSKH!$A:$B,2,0) -> A-29 | C84: =IF(AND(D84<>"", F84<>""), "DIỆU", "") -> DIỆU | D84: DELTA-TQVĐ | E84: =IF(LEFT(F84,1)="1","N","X") -> X | F84: 308220412160 | G84: B11 | H84: 46083 | I84: NL | J84: V | K84: TN | M84: 34DW-SSC/26 | O84: 265598616 | Q84: 1 | U84: HASU5106917 | X84: ĐỒNG NAI
A85: =ROW( ) -3 -> 82 | B85: =VLOOKUP(D85,DSKH!$A:$B,2,0) -> A-29 | C85: =IF(AND(D85<>"", F85<>""), "DIỆU", "") -> DIỆU | D85: DELTA-TQVĐ | E85: =IF(LEFT(F85,1)="1","N","X") -> X | F85: 308227935100 | G85: B11 | H85: 46144 | I85: NL | J85: V | K85: TN | M85: 40DW-SSC/26 | O85: 235600170876 | Q85: 1 | U85: MRSU5457681 | V85: 202610937831 | W85: 500000 | X85: CÁT LÁI
A86: =ROW( ) -3 -> 83 | B86: =VLOOKUP(D86,DSKH!$A:$B,2,0) -> A-29 | C86: =IF(AND(D86<>"", F86<>""), "DIỆU", "") -> DIỆU | D86: DELTA-TQVĐ | E86: =IF(LEFT(F86,1)="1","N","X") -> X | F86: 308227827040 | G86: B11 | H86: 46144 | I86: NL | J86: V | K86: TN | M86: 39DW-SSC/26 | O86: SGN3052400 | Q86: 1 | U86: MRKU4779823 | X86: ĐỒNG NAI
A87: =ROW( ) -3 -> 84 | B87: =VLOOKUP(D87,DSKH!$A:$B,2,0) -> A-29 | C87: =IF(AND(D87<>"", F87<>""), "DIỆU", "") -> DIỆU | D87: DELTA-TQVĐ | E87: =IF(LEFT(F87,1)="1","N","X") -> X | F87: 308223534420 | G87: B11 | H87: 46114 | I87: NL | J87: V | K87: TN | M87: 36DW-SSC/26 | O87: 265598616 | Q87: 1 | U87: MSKU1101304 | X87: ĐỒNG NAI
A88: =ROW( ) -3 -> 85 | B88: =VLOOKUP(D88,DSKH!$A:$B,2,0) -> A-29 | C88: =IF(AND(D88<>"", F88<>""), "DIỆU", "") -> DIỆU | D88: DELTA-TQVĐ | E88: =IF(LEFT(F88,1)="1","N","X") -> X | F88: 308223760150 | G88: B11 | H88: 46114 | I88: NL | J88: V | K88: TN | M88: 38DW-SSC/26 | O88: 265598616 | Q88: 1 | U88: CAIU9307704 | X88: ĐỒNG NAI
A89: =ROW( ) -3 -> 86 | B89: =VLOOKUP(D89,DSKH!$A:$B,2,0) -> A-29 | C89: =IF(AND(D89<>"", F89<>""), "DIỆU", "") -> DIỆU | D89: DELTA-TQVĐ | E89: =IF(LEFT(F89,1)="1","N","X") -> X | F89: 308223652240 | G89: B11 | H89: 46114 | I89: NL | J89: V | K89: TN | M89: 37DW-SSC/26 | O89: 265598616 | Q89: 1 | U89: EGSU1216665 | X89: ĐỒNG NAI
A90: =ROW( ) -3 -> 87 | B90: =VLOOKUP(D90,DSKH!$A:$B,2,0) -> A-519 | C90: =IF(AND(D90<>"", F90<>""), "DIỆU", "") -> DIỆU | D90: TONG HONG | E90: =IF(LEFT(F90,1)="1","N","X") -> X | F90: 308226542430 | G90: E52 | H90: 46114 | I90: NL | J90: X | K90: NT | M90: 20260202002 | S90: 1
A91: =ROW( ) -3 -> 88 | B91: =VLOOKUP(D91,DSKH!$A:$B,2,0) -> A-519 | C91: =IF(AND(D91<>"", F91<>""), "DIỆU", "") -> DIỆU | D91: TONG HONG | E91: =IF(LEFT(F91,1)="1","N","X") -> X | F91: 308225108460 | G91: E52 | H91: 46114 | I91: NL | J91: X | K91: NT | M91: 20260204001 | S91: 1
A92: =ROW( ) -3 -> 89 | B92: =VLOOKUP(D92,DSKH!$A:$B,2,0) -> A-212 | C92: =IF(AND(D92<>"", F92<>""), "DIỆU", "") -> DIỆU | D92: LEADER | E92: =IF(LEFT(F92,1)="1","N","X") -> N | F92: 107960319610 | G92: E15 | H92: 46114 | I92: NL | J92: X | K92: TN | M92: 83 | S92: 1
A93: =ROW( ) -3 -> 90 | B93: =VLOOKUP(D93,DSKH!$A:$B,2,0) -> A-212 | C93: =IF(AND(D93<>"", F93<>""), "DIỆU", "") -> DIỆU | D93: LEADER | E93: =IF(LEFT(F93,1)="1","N","X") -> N | F93: 107960293230 | G93: E15 | H93: 46114 | I93: NL | J93: X | K93: TN | M93: 148 | S93: 1
A94: =ROW( ) -3 -> 91 | B94: =VLOOKUP(D94,DSKH!$A:$B,2,0) -> A-212 | C94: =IF(AND(D94<>"", F94<>""), "DIỆU", "") -> DIỆU | D94: LEADER | E94: =IF(LEFT(F94,1)="1","N","X") -> N | F94: 107960268140 | G94: E15 | H94: 46114 | I94: NL | J94: X | K94: TN | M94: 50 | S94: 1
A95: =ROW( ) -3 -> 92 | B95: =VLOOKUP(D95,DSKH!$A:$B,2,0) -> A-212 | C95: =IF(AND(D95<>"", F95<>""), "DIỆU", "") -> DIỆU | D95: LEADER | E95: =IF(LEFT(F95,1)="1","N","X") -> N | F95: 107960250200 | G95: E15 | H95: 46114 | I95: NL | J95: X | K95: TN | M95: 237 | S95: 1
A96: =ROW( ) -3 -> 93 | B96: =VLOOKUP(D96,DSKH!$A:$B,2,0) -> A-212 | C96: =IF(AND(D96<>"", F96<>""), "DIỆU", "") -> DIỆU | D96: LEADER | E96: =IF(LEFT(F96,1)="1","N","X") -> N | F96: 107960230600 | G96: E15 | H96: 46114 | I96: NL | J96: V | K96: TN | M96: 237 | S96: 1
A97: =ROW( ) -3 -> 94 | B97: =VLOOKUP(D97,DSKH!$A:$B,2,0) -> A-212 | C97: =IF(AND(D97<>"", F97<>""), "DIỆU", "") -> DIỆU | D97: LEADER | E97: =IF(LEFT(F97,1)="1","N","X") -> N | F97: 107960185210 | G97: E15 | H97: 46114 | I97: NL | J97: X | K97: TN | M97: 368 | S97: 1
A98: =ROW( ) -3 -> 95 | B98: =VLOOKUP(D98,DSKH!$A:$B,2,0) -> A-212 | C98: =IF(AND(D98<>"", F98<>""), "DIỆU", "") -> DIỆU | D98: LEADER | E98: =IF(LEFT(F98,1)="1","N","X") -> N | F98: 107960160560 | G98: E15 | H98: 46114 | I98: NL | J98: X | K98: TN | M98: 49 | S98: 1
A99: =ROW( ) -3 -> 96 | B99: =VLOOKUP(D99,DSKH!$A:$B,2,0) -> A-212 | C99: =IF(AND(D99<>"", F99<>""), "DIỆU", "") -> DIỆU | D99: LEADER | E99: =IF(LEFT(F99,1)="1","N","X") -> N | F99: 107960128510 | G99: E15 | H99: 46114 | I99: NL | J99: X | K99: TN | M99: 49 | S99: 1
A100: =ROW( ) -3 -> 97 | B100: =VLOOKUP(D100,DSKH!$A:$B,2,0) -> A-212 | C100: =IF(AND(D100<>"", F100<>""), "DIỆU", "") -> DIỆU | D100: LEADER | E100: =IF(LEFT(F100,1)="1","N","X") -> N | F100: 107960063260 | G100: E15 | H100: 46114 | I100: NL | J100: X | K100: TN | M100: 37 | S100: 1
A101: =ROW( ) -3 -> 98 | B101: =VLOOKUP(D101,DSKH!$A:$B,2,0) -> A-212 | C101: =IF(AND(D101<>"", F101<>""), "DIỆU", "") -> DIỆU | D101: LEADER | E101: =IF(LEFT(F101,1)="1","N","X") -> N | F101: 107960019160 | G101: E15 | H101: 46114 | I101: NL | J101: X | K101: TN | M101: 109 | S101: 1
...

Sheet THÁNG 3_Tổng hợp
A1: STT | B1: MÃ KHÁCH HÀNG | C1: NHÂN VIÊN | D1: KHÁCH HÀNG | E1: CÔNG VIỆC | F1: SỐ TỜ KHAI | G1: LOẠI HÌNH | H1: NGÀY TỜ KHAI | I1: LOẠI HÀNG | J1: LUỒNG TK | K1: HẢI QUAN | L1: C/O | M1: SỐ INV/VAT | N1: SỐ BILL | O1: SỐ BOOKING | P1: SỐ LƯỢNG | T1: (KIỆN, KG) | U1: SỐ CONTAINER | V1: THÔNG BÁO PHÍ CSHT | W1: SỐ TIỀN CSHT | X1: CẢNG XUẤT - CẢNG NHẬP | Y1: GHI CHÚ
P2: 20' | Q2: 40' | R2: LCL | S2: TC
A4: =ROW( ) -3 -> 1 | B4: =VLOOKUP(D4,DSKH!$A:$B,2,0) -> #N/A | C4: KHÁCH | D4: TÂN PHÚ VN | E4: X | F4: 308298297700 | G4: E62 | H4: 46086 | I4: NL | J4: X | K4: BH | M4: 126/EXP-2026 | Q4: 1 | U4: APZU4765152 | X4: CÁI MÉP
A5: =ROW( ) -3 -> 2 | B5: =VLOOKUP(D5,DSKH!$A:$B,2,0) -> A-39 | C5: KHÁCH | D5: TIGER | E5: N | F5: 108000946324 | G5: H11 | H5: 46079 | I5: NL | J5: D | K5: BH | M5: TG-HCM-370/25-3 | N5: NGODJZ29396-01 | P5: 1 | U5: OOCU0401133 | V5: V3PHT202611107941 | W5: 250000 | X5: SP-ITC | Y5: CHUNG LÔ
A6: =ROW( ) -3 -> 3 | B6: =VLOOKUP(D6,DSKH!$A:$B,2,0) -> A-39 | C6: KHÁCH | D6: TIGER | E6: N | F6: 108000993000 | G6: E31 | H6: 46079 | I6: NL | J6: X | K6: BH | M6: FL-HCM-188/25 | N6: NGODJZ29013
A7: =ROW( ) -3 -> 4 | B7: =VLOOKUP(D7,DSKH!$A:$B,2,0) -> A-39 | C7: KHÁCH | D7: TIGER | E7: N | F7: 108000906860 | G7: E31 | H7: 46079 | I7: NL | J7: X | K7: BH | M7: TG-HCM-370/25-1 | N7: NGODJZ29396-02
A8: =ROW( ) -3 -> 5 | B8: =VLOOKUP(D8,DSKH!$A:$B,2,0) -> A-17 | C8: KHÁCH | D8: NHỰA RELIABLE | E8: N | F8: 108013274020 | G8: A12 | H8: 46083 | I8: NL | J8: V | K8: BH | L8: D | M8: SQZSE-26-0444-3 | N8: SE26020077-01 | Q8: 1 | U8: OOLU4446750 | X8: CÁT LÁI
A9: =ROW( ) -3 -> 6 | B9: =VLOOKUP(D9,DSKH!$A:$B,2,0) -> A-17 | C9: KHÁCH | D9: NHỰA RELIABLE | E9: N | F9: 108013247640 | G9: A12 | H9: 46083 | I9: NL | J9: V | K9: BH | L9: E | M9: INVJYSP260114ZKXS-2325 | N9: 263837697 | Q9: 5 | U9: MSKU1898440 UETU7591993 MSKU1944021 MRSU7567395 MRKU3943296 | V9: V3PHT265254146033 | W9: 2500000 | X9: CÁT LÁI
A10: =ROW( ) -3 -> 7 | B10: =VLOOKUP(D10,DSKH!$A:$B,2,0) -> A-17 | C10: KHÁCH | D10: NHỰA RELIABLE | E10: N | F10: 108013214520 | G10: A12 | H10: 46083 | I10: NL | J10: V | K10: BH | L10: E | M10: INVJYSP260114ZKXS-2323 | N10: 263837670 | Q10: 5 | U10: TCNU1127910 MSKU1585370 HASU4271835 MSKU0223102 MRSU4245646 | V10: V3PHT265250306422 | W10: 2500000 | X10: CÁT LÁI
A11: =ROW( ) -3 -> 8 | B11: =VLOOKUP(D11,DSKH!$A:$B,2,0) -> A-27 | C11: KHÁCH | D11: TRUNG ĐÔNG | E11: N | F11: 108016254840 | G11: E31 | H11: 46084 | I11: NL | J11: X | K11: DN3 | M11: 9670092423 | N11: HDMUDMMA83529200 | Q11: 20 | U11: BMOU5178701 CLKU5017800 HMMU4458286 HMMU4898990 HMMU4977260 HMMU6225679 HMMU6428589 HMMU6445014 HMMU6647490 HMMU6881661 HMMU6895515 HMMU6967615 HMMU7144864 HMMU7169754 KOCU4165828 KOCU4394228 KOCU4741923 KOCU4853939 KOCU5054285 TLLU5814541 | V11: V3PHT202611092966 | W11: 10000000 | X11: CÁT LÁI
A12: =ROW( ) -3 -> 9 | B12: =VLOOKUP(D12,DSKH!$A:$B,2,0) -> A-27 | C12: KHÁCH | D12: TRUNG ĐÔNG | E12: N | F12: 108017990950 | G12: A12 | H12: 46084 | I12: NL | J12: V | K12: DN3 | L12: KV | M12: 40144040 | N12: 265589867 | Q12: 10 | U12: SUDU8984797 MRSU3753262 CAAU9001814 GCXU6390655 CAAU6574582 TCKU6962640 SUDU8801710 MRSU5311763 GCXU5717126 TCNU8805305 | V12: V3PHT202611097908 | W12: 5000000 | X12: CÁT LÁI
A13: =ROW( ) -3 -> 10 | B13: =VLOOKUP(D13,DSKH!$A:$B,2,0) -> A-17 | C13: KHÁCH | D13: NHỰA RELIABLE | E13: N | F13: 108023275360 | G13: A12 | H13: 46086 | I13: NL | J13: V | K13: BH | L13: D | M13: SQZSE-26-0444-1 | N13: EGLV070600043187 | Q13: 4 | U13: CAAU6887885 EGSU1831577 EITU9647028 TXGU6094237 | V13: V3PHT202611110739 | W13: 2000000 | X13: CÁT LÁI
A14: =ROW( ) -3 -> 11 | B14: =VLOOKUP(D14,DSKH!$A:$B,2,0) -> A-17 | C14: KHÁCH | D14: NHỰA RELIABLE | E14: N | F14: 108015527800 | G14: A12 | H14: 46084 | I14: NL | J14: V | K14: BH | L14: D | M14: SQZSE-26-0444-4 | N14: SE26020105 | Q14: 1 | U14: DRYU4246145 | V14: V3PHT202611094047 | W14: 500000 | X14: CÁT LÁI
A15: =ROW( ) -3 -> 12 | B15: =VLOOKUP(D15,DSKH!$A:$B,2,0) -> A-27 | C15: KHÁCH | D15: TRUNG ĐÔNG | E15: N | F15: 108020834500 | G15: E31 | H15: 46085 | I15: NL | J15: X | K15: DN3 | M15: IT-SI-11903 | N15: HDMUDMMA40471100 | Q15: 20 | U15: BMOU5173870 GCXU5034135 HMMU4149245 HMMU4170181 HMMU4291408 HMMU4669653 HMMU4670124 HMMU4680591 HMMU4868070 HMMU4941627 HMMU4941822 HMMU6577324 HMMU6662405 HMMU6792461 HMMU6909500 HMMU7097171 KOCU4114965 KOCU4204164 KOCU4909112 TLLU5293931 | V15: V3PHT202611105165 | W15: 10000000 | X15: CÁT LÁI
A16: =ROW( ) -3 -> 13 | B16: =VLOOKUP(D16,DSKH!$A:$B,2,0) -> #N/A | C16: KHÁCH | D16: YIYAO | E16: KBS | F16: 308258035060 | K16: NT | Y16: 730439902840
A17: =ROW( ) -3 -> 14 | B17: =VLOOKUP(D17,DSKH!$A:$B,2,0) -> #N/A | C17: THÚY | D17: ĐầU Tư Và XâY LắP SàI GòN | E17: N | F17: 108020846730 | G17: G13 | H17: 46085 | I17: MM | J17: D | K17: NT | M17: OTM-SG-260225 | S17: 1
A18: =ROW( ) -3 -> 15 | B18: =VLOOKUP(D18,DSKH!$A:$B,2,0) -> #N/A | C18: THÚY | D18: TALLER - GUG | E18: N | F18: 108028244920 | G18: E13 | H18: 46087 | I18: MM | J18: V | K18: MP | M18: 26HY018D002 | N18: NBFCL26020433 | Q18: 2 | U18: FFAU5015768 SEKU6390830 | V18: CHỜ XÁC ĐỊNH RỒI ĐÓNG SAU | X18: CÁT LÁI
A19: =ROW( ) -3 -> 16 | B19: =VLOOKUP(D19,DSKH!$A:$B,2,0) -> A-324 | C19: HOÀI | D19: SCHAEFFLER | E19: N | F19: 108012829410 | G19: E31 | H19: 46083 | I19: NL | J19: X | K19: BH | M19: 137597374 | N19: I489812 | R19: 1 | T19: 1K/ 6KG | X19: KHO SCSC
A20: =ROW( ) -3 -> 17 | B20: =VLOOKUP(D20,DSKH!$A:$B,2,0) -> A-324 | C20: HOÀI | D20: SCHAEFFLER | E20: N | F20: 108012831840 | G20: E31 | H20: 46083 | I20: NL | J20: X | K20: BH | M20: 137597374 | N20: I497946 | R20: 1 | T20: 3K/ 224.2KG | X20: KHO SCSC | Y20: CHUNG BL
A21: =ROW( ) -3 -> 18 | B21: =VLOOKUP(D21,DSKH!$A:$B,2,0) -> A-324 | C21: HOÀI | D21: SCHAEFFLER | E21: N | F21: 108012834200 | G21: A41 | H21: 46083 | I21: NL | J21: V | K21: BH | M21: 137597374 | N21: I497946
A22: =ROW( ) -3 -> 19 | B22: =VLOOKUP(D22,DSKH!$A:$B,2,0) -> A-324 | C22: HOÀI | D22: SCHAEFFLER | E22: N | F22: 108014581730 | G22: E31 | H22: 46083 | I22: NL | J22: X | K22: BH | M22: 137597374 | N22: I468026 | R22: 1 | T22: 11K/ 229KG | X22: KHO SCSC
A23: =ROW( ) -3 -> 20 | B23: =VLOOKUP(D23,DSKH!$A:$B,2,0) -> A-324 | C23: HOÀI | D23: SCHAEFFLER | E23: N | F23: 108014589760 | G23: E31 | H23: 46083 | I23: NL | J23: X | K23: BH | M23: 137597374 | N23: I443493 | R23: 1 | T23: 4K/ 118KG | X23: KHO SCSC
A24: =ROW( ) -3 -> 21 | B24: =VLOOKUP(D24,DSKH!$A:$B,2,0) -> A-324 | C24: HOÀI | D24: SCHAEFFLER | E24: N | F24: 108014590610 | G24: A41 | H24: 46083 | I24: NL | J24: V | K24: BH | M24: 137597374 | N24: I443308 | R24: 1 | T24: 4K/ 45.9KG | X24: KHO SCSC | Y24: CHUNG BL
A25: =ROW( ) -3 -> 22 | B25: =VLOOKUP(D25,DSKH!$A:$B,2,0) -> A-324 | C25: HOÀI | D25: SCHAEFFLER | E25: N | F25: 108014593150 | G25: A12 | H25: 46083 | I25: NL | J25: X | K25: BH | M25: 137597374
A26: =ROW( ) -3 -> 23 | B26: =VLOOKUP(D26,DSKH!$A:$B,2,0) -> A-324 | C26: HOÀI | D26: SCHAEFFLER | E26: N | F26: 108015864940 | G26: A12 | H26: 46083 | I26: NL | J26: X | K26: BH | M26: 137597374 | N26: 712659987501 | R26: 1 | T26: 9K/ 9.3KG | X26: KHO FEDEX
A27: =ROW( ) -3 -> 24 | B27: =VLOOKUP(D27,DSKH!$A:$B,2,0) -> A-324 | C27: HOÀI | D27: SCHAEFFLER | E27: N | F27: 108015883360 | G27: A12 | H27: 46083 | I27: NL | J27: V | K27: BH | L27: REX | M27: 137597374 | N27: I487392 | R27: 1 | T27: 1K/ 338KG | X27: KHO SCSC
A28: =ROW( ) -3 -> 25 | B28: =VLOOKUP(D28,DSKH!$A:$B,2,0) -> A-650 | C28: HOÀI | D28: BRONCO | E28: X | F28: 308279208550 | G28: E42 | H28: 46083 | I28: NL | J28: Đ | K28: TN | M28: 1 | S28: 1 | T28: 263K/1993.98KG
A29: =ROW( ) -3 -> 26 | B29: =VLOOKUP(D29,DSKH!$A:$B,2,0) -> A-15 | C29: HOÀI | D29: PENFLEX | E29: N | F29: 108016916930 | G29: A12 | H29: 46083 | I29: NL | J29: X | K29: TN | M29: P7900 | N29: 889091427627 | R29: 1 | T29: 1K/ 5.5KG | X29: KHO FEDEX
A30: =ROW( ) -3 -> 27 | B30: =VLOOKUP(D30,DSKH!$A:$B,2,0) -> A-15 | C30: HOÀI | D30: PENFLEX | E30: N | F30: 108016959300 | G30: A12 | H30: 46083 | I30: NL | J30: X | K30: TN | M30: RE/2026091 | N30: 888747229609 | R30: 1 | T30: 1K/ 11KG | X30: KHO FEDEX
A31: =ROW( ) -3 -> 28 | B31: =VLOOKUP(D31,DSKH!$A:$B,2,0) -> A-15 | C31: HOÀI | D31: PENFLEX | E31: N | F31: 108017010620 | G31: A12 | H31: 46083 | I31: NL | J31: X | K31: TN | M31: 3 | N31: 888982402513 | R31: 1 | T31: 1K/ 3KG | X31: KHO FEDEX
A32: =ROW( ) -3 -> 29 | B32: =VLOOKUP(D32,DSKH!$A:$B,2,0) -> A-37 | C32: HOÀI | D32: FLEMING | E32: X | F32: 308291037410 | G32: E42 | H32: 46085 | I32: NL | J32: X | K32: CX | M32: PB-2512004/005/008-2/009-2 | R32: 1 | T32: 202K/ 11009.46KG/3.97CBM | X32: TBS
A33: =ROW( ) -3 -> 30 | B33: =VLOOKUP(D33,DSKH!$A:$B,2,0) -> A-37 | C33: HOÀI | D33: FLEMING | E33: X | F33: 308285431440 | G33: E42 | H33: 46083 | I33: NL | J33: X | K33: CX | M33: HSH-2510015-2508150/3 | O33: SGN3065610 | P33: 1 | T33: 688K/ 5944.32KG/26.523CBM | U33: WNGU2593870 | X33: BINH DUONG
A34: =ROW( ) -3 -> 31 | B34: =VLOOKUP(D34,DSKH!$A:$B,2,0) -> A-37 | C34: HOÀI | D34: FLEMING | E34: X | F34: 308285372050 | G34: E42 | H34: 46083 | I34: NL | J34: X | K34: CX | M34: HSH-2510015-2508150/1 | O34: SGN3065610 | Q34: 1 | T34: 1540K/ 19388.6KG/59CBM | U34: TCLU1848458 | X34: BINH DUONG
A35: =ROW( ) -3 -> 32 | B35: =VLOOKUP(D35,DSKH!$A:$B,2,0) -> A-37 | C35: HOÀI | D35: FLEMING | E35: X | F35: 308285399020 | G35: E42 | H35: 46083 | I35: NL | J35: X | K35: CX | M35: HSH-2510015-2508150/2 | O35: SGN3065610 | Q35: 1 | T35: 1232K/ 9440.2KG/59.377CBM | U35: CMAU4842070 | X35: BINH DUONG
A36: =ROW( ) -3 -> 33 | B36: =VLOOKUP(D36,DSKH!$A:$B,2,0) -> A-37 | C36: HOÀI | D36: FLEMING | E36: X | F36: 308291498820 | G36: E42 | H36: 46085 | I36: NL | J36: X | K36: CX | M36: HSH-2508150/2 | R36: 1 | T36: 185K/ 1598.4KG/7.132CBM | X36: TBS
A37: =ROW( ) -3 -> 34 | B37: =VLOOKUP(D37,DSKH!$A:$B,2,0) -> A-37 | C37: HOÀI | D37: FLEMING | E37: X | F37: 308291534630 | G37: E42 | H37: 46085 | I37: NL | J37: X | K37: CX | M37: HSH-2508150/1 | R37: 1 | T37: 154K/ 1330.56KG/5.937CBM | X37: TBS
A38: =ROW( ) -3 -> 35 | B38: =VLOOKUP(D38,DSKH!$A:$B,2,0) -> A-131 | C38: HOÀI | D38: OPTIMA/LYNN | E38: X | F38: 308283884700 | G38: B11 | H38: 46083 | I38: NL | J38: X | K38: DN3 | M38: 8650203516 | O38: 235600328186 | Q38: 1 | T38: 1750K/ 6388KG | U38: TCNU2122512 | V38: 202611081333 | W38: 500000 | X38: CAT LAI
A39: =ROW( ) -3 -> 36 | B39: =VLOOKUP(D39,DSKH!$A:$B,2,0) -> A-131 | C39: HOÀI | D39: OPTIMA/LYNN | E39: X | F39: 308284068910 | G39: B11 | H39: 46083 | I39: NL | J39: X | K39: DN3 | M39: 8650203739 | R39: 1 | T39: 700K/ 3344KG | X39: TBS
A40: =ROW( ) -3 -> 37 | B40: =VLOOKUP(D40,DSKH!$A:$B,2,0) -> A-131 | C40: HOÀI | D40: OPTIMA/LYNN | E40: X | F40: 308288040710 | G40: B11 | H40: 46084 | I40: NL | J40: X | K40: DN3 | M40: 8650203742 | R40: 1 | T40: 696K/ 3503KG | X40: TBS
A41: =ROW( ) -3 -> 38 | B41: =VLOOKUP(D41,DSKH!$A:$B,2,0) -> A-131 | C41: HOÀI | D41: OPTIMA/LYNN | E41: X | F41: 308290430030 | G41: B11 | H41: 46084 | I41: NL | J41: X | K41: DN3 | M41: 8650204322 | O41: SGNM91458500 | Q41: 1 | T41: 1356K/ 7284KG | U41: GAOU6187749 | V41: 202611098302 | W41: 500000 | X41: CANG PHUOC LONG
A42: =ROW( ) -3 -> 39 | B42: =VLOOKUP(D42,DSKH!$A:$B,2,0) -> A-131 | C42: HOÀI | D42: OPTIMA/LYNN | E42: X | F42: 308291975040 | G42: B11 | H42: 46085 | I42: NL | J42: X | K42: DN3 | M42: 8650203740 | R42: 1 | T42: 691K/ 3275KG | X42: TBS
A43: =ROW( ) -3 -> 40 | B43: =VLOOKUP(D43,DSKH!$A:$B,2,0) -> A-131 | C43: HOÀI | D43: OPTIMA/LYNN | E43: X | F43: 308292075250 | G43: B11 | H43: 46085 | I43: NL | J43: X | K43: DN3 | M43: 8650203518 | O43: 32417218 | Q43: 1 | T43: 948K/ 5963KG | U43: GCXU5909303 | V43: 202611101906 | W43: 500000 | X43: PHUC LONG ICD
A44: =ROW( ) -3 -> 41 | B44: =VLOOKUP(D44,DSKH!$A:$B,2,0) -> A-131 | C44: HOÀI | D44: OPTIMA/LYNN | E44: X | F44: 308292159950 | G44: B11 | H44: 46085 | I44: NL | J44: X | K44: DN3 | M44: 8650203515 | Q44: 1 | T44: 620K/ 9052KG | U44: EGHU9823194 | V44: 202611102080 | W44: 500000 | X44: CAT LAI
A45: =ROW( ) -3 -> 42 | B45: =VLOOKUP(D45,DSKH!$A:$B,2,0) -> A-650 | C45: HOÀI | D45: BRONCO | E45: X | F45: 308292681600 | G45: E42 | H45: 46085 | I45: NL | J45: X | K45: TN | M45: 2 | S45: 1 | T45: 571K/4284.5KG
A46: =ROW( ) -3 -> 43 | B46: =VLOOKUP(D46,DSKH!$A:$B,2,0) -> A-16 | C46: HOÀI | D46: PHÚ GIA PHÁT | E46: X | F46: 308294501710 | G46: B11 | H46: 46086 | I46: NL | J46: X | K46: CX | M46: 5 | S46: 1 | T46: 90K/ 900KG
A47: =ROW( ) -3 -> 44 | B47: =VLOOKUP(D47,DSKH!$A:$B,2,0) -> A-131 | C47: HOÀI | D47: OPTIMA/LYNN | E47: X | F47: 308299412060 | G47: B11 | H47: 46087 | I47: NL | J47: X | K47: DN3 | M47: 8650203732 | R47: 1 | T47: 108K/ 934KG | X47: TBS
A48: =ROW( ) -3 -> 45 | B48: =VLOOKUP(D48,DSKH!$A:$B,2,0) -> A-15 | C48: HOÀI | D48: PENFLEX | E48: N | F48: 108025768060 | G48: E31 | H48: 46087 | I48: NL | J48: V | K48: TN | L48: KV | M48: CIPEN260224-01 | N48: TWAY260227HOC001 | P48: 1 | T48: 1K/ 3KG | U48: TGCU2400129 | V48: 202611117374 | W48: 250000 | X48: CAT LAI
A49: =ROW( ) -3 -> 46 | B49: =VLOOKUP(D49,DSKH!$A:$B,2,0) -> B-57 | C49: HÀ | D49: NEW-TQQT | E49: X | F49: 308286078350 | G49: E42 | H49: 46083 | I49: NL | J49: X | K49: CX | M49: NEW4326 | O49: SGNG36057700 | Q49: 1 | T49: 46PK/19727.38KG | U49: TLLU1569580 | X49: ĐỒNG NAI
A50: =ROW( ) -3 -> 47 | B50: =VLOOKUP(D50,DSKH!$A:$B,2,0) -> B-57 | C50: HÀ | D50: NEW-TQQT | E50: X | F50: 308286043940 | G50: E42 | H50: 46083 | I50: NL | J50: X | K50: CX | M50: NEW4327 | Q50: 1 | T50: 48PK/19653.97KG | U50: TLLU6087278 | X50: ĐỒNG NAI
A51: =ROW( ) -3 -> 48 | B51: =VLOOKUP(D51,DSKH!$A:$B,2,0) -> B-57 | C51: HÀ | D51: HONGSEN - TQQT | E51: X | F51: 308285116220 | G51: B11 | H51: 46083 | I51: NL | J51: X | K51: TN | M51: 77 | S51: 1 | T51: 353PK/2532.54KG
A52: =ROW( ) -3 -> 49 | B52: =VLOOKUP(D52,DSKH!$A:$B,2,0) -> B-57 | C52: HÀ | D52: HONGSEN - TQQT | E52: X | F52: 308285209650 | G52: B11 | H52: 46083 | I52: NL | J52: X | K52: TN | M52: 78 | S52: 1 | T52: 5PK/33.21KG
A53: =ROW( ) -3 -> 50 | B53: =VLOOKUP(D53,DSKH!$A:$B,2,0) -> B-57 | C53: HÀ | D53: HONGSEN - TQQT | E53: X | F53: 308285262520 | G53: B11 | H53: 46083 | I53: NL | J53: X | K53: TN | M53: 79 | S53: 1 | T53: 132PK/965.64KG
A54: =ROW( ) -3 -> 51 | B54: =VLOOKUP(D54,DSKH!$A:$B,2,0) -> A-324 | C54: HÀ | D54: SCHAEFFLER | E54: X | F54: 308284965610 | G54: E62 | H54: 46083 | I54: NL | J54: X | K54: BH | M54: SHANGHAI-26.W10-05-0203 | O54: SGN01020739 | P54: 1 | T54: 55PP/8026KG | U54: FTAU1749210 | X54: CÁT LÁI | Y54: CHUNG CONT
A55: =ROW( ) -3 -> 52 | B55: =VLOOKUP(D55,DSKH!$A:$B,2,0) -> A-324 | C55: HÀ | D55: SCHAEFFLER | E55: X | F55: 308284964320 | G55: E62 | H55: 46083 | I55: NL | J55: X | K55: BH
A56: =ROW( ) -3 -> 53 | B56: =VLOOKUP(D56,DSKH!$A:$B,2,0) -> A-29 | C56: HÀ | D56: GIPT - TQVĐ | E56: N | F56: 108012035240 | G56: E31 | H56: 46083 | I56: NL | J56: X | K56: TN | M56: GIPT20260123 | N56: JPC2026012351 | R56: 1 | T56: 3CS/2995KG | X56: CÁT LÁI | Y56: KBHC:CBHC-2026-010741
A57: =ROW( ) -3 -> 54 | B57: =VLOOKUP(D57,DSKH!$A:$B,2,0) -> A-29 | C57: HÀ | D57: GIPT - TQVĐ | E57: N | F57: 108013572220 | G57: E31 | H57: 46083 | I57: NL | J57: X | K57: TN | M57: 58913320 | N57: 889091761642 | R57: 1 | T57: 2PK/24KG | X57: FEDEX
A58: =ROW( ) -3 -> 55 | B58: =VLOOKUP(D58,DSKH!$A:$B,2,0) -> A-29 | C58: HÀ | D58: GIPT - TQVĐ | E58: X | F58: 308283309410 | G58: E62 | H58: 46083 | I58: NL | J58: X | K58: TN | M58: TIT260301 | R58: 1 | T58: 8PP/2801.21KG | X58: KNQ
A59: =ROW( ) -3 -> 56 | B59: =VLOOKUP(D59,DSKH!$A:$B,2,0) -> A-383 | C59: HÀ | D59: JV | E59: X | F59: 308289962100 | G59: E62 | H59: 46084 | I59: NL | J59: X | K59: TN | M59: JV-PANARUB-20260303-A | R59: 1 | T59: 1CT/3.3KG | X59: DHL
A60: =ROW( ) -3 -> 57 | B60: =VLOOKUP(D60,DSKH!$A:$B,2,0) -> A-29 | C60: HÀ | D60: GIPT - TQVĐ | E60: X | F60: 308288979960 | G60: E62 | H60: 46084 | I60: NL | J60: X | K60: TN | M60: WLV260301 | R60: 1 | T60: 10PP/5183.7KG | X60: KNQ
A61: =ROW( ) -3 -> 58 | B61: =VLOOKUP(D61,DSKH!$A:$B,2,0) -> B-57 | C61: HÀ | D61: HONGSEN - TQQT | E61: X | F61: 308288687730 | G61: B11 | H61: 46084 | I61: NL | J61: X | K61: TN | M61: 80 | S61: 1 | T61: 830PK/7160.34KG
A62: =ROW( ) -3 -> 59 | B62: =VLOOKUP(D62,DSKH!$A:$B,2,0) -> B-57 | C62: HÀ | D62: HONGSEN - TQQT | E62: X | F62: 308288697050 | G62: B11 | H62: 46084 | I62: NL | J62: X | K62: TN | M62: 81 | S62: 1 | T62: 934PK/8045.34KG
A63: =ROW( ) -3 -> 60 | B63: =VLOOKUP(D63,DSKH!$A:$B,2,0) -> B-57 | C63: HÀ | D63: HONGSEN - TQQT | E63: X | F63: 308288703460 | G63: B11 | H63: 46084 | I63: NL | J63: X | K63: TN | M63: 82 | S63: 1 | T63: 1125PK/6236.25KG
A64: =ROW( ) -3 -> 61 | B64: =VLOOKUP(D64,DSKH!$A:$B,2,0) -> B-57 | C64: HÀ | D64: HONGSEN - TQQT | E64: X | F64: 308289502420 | G64: B11 | H64: 46084 | I64: NL | J64: X | K64: TN | M64: 83 | S64: 1 | T64: 678PK/3938.03KG
A65: =ROW( ) -3 -> 62 | B65: =VLOOKUP(D65,DSKH!$A:$B,2,0) -> A-324 | C65: HÀ | D65: SCHAEFFLER | E65: X | F65: 308286942630 | G65: E62 | H65: 46084 | I65: NL | J65: X | K65: BH | M65: 6603066942 | O65: 83539081 | R65: 1 | T65: 6PP/488KG | X65: CÁT LÁI
A66: =ROW( ) -3 -> 63 | B66: =VLOOKUP(D66,DSKH!$A:$B,2,0) -> A-324 | C66: HÀ | D66: SCHAEFFLER | E66: X | F66: 308286955710 | G66: E62 | H66: 46084 | I66: NL | J66: X | K66: BH | M66: 6603066943+6603066944 | O66: SGNTYO158572V | R66: 1 | T66: 5PP/425KG | X66: CÁT LÁI
A67: =ROW( ) -3 -> 64 | B67: =VLOOKUP(D67,DSKH!$A:$B,2,0) -> A-324 | C67: HÀ | D67: SCHAEFFLER | E67: X | F67: 308286958620 | G67: E62 | H67: 46084 | I67: NL | J67: X | K67: BH | M67: 6603066895 | O67: 83539079 | R67: 1 | T67: 1PP/28KG | X67: CÁT LÁI
A68: =ROW( ) -3 -> 65 | B68: =VLOOKUP(D68,DSKH!$A:$B,2,0) -> A-324 | C68: HÀ | D68: SCHAEFFLER | E68: X | F68: 308286959210 | G68: E62 | H68: 46084 | I68: NL | J68: X | K68: BH | M68: 6603066997 | O68: SGN0432859 | R68: 1 | T68: 1PP/49KG | X68: TCS
A69: =ROW( ) -3 -> 66 | B69: =VLOOKUP(D69,DSKH!$A:$B,2,0) -> A-361 | C69: HÀ | D69: HANSUNG - FORMAN | E69: N | F69: 108020667420 | G69: A12 | H69: 46085 | I69: NL | J69: X | K69: TDM | M69: MS-260209-04 | N69: 889090274826 | R69: 1 | T69: 1PK/5KG | X69: FEDEX
A70: =ROW( ) -3 -> 67 | B70: =VLOOKUP(D70,DSKH!$A:$B,2,0) -> A-361 | C70: HÀ | D70: HANSUNG - FORMAN | E70: N | F70: 108022975540 | G70: A12 | H70: 46086 | I70: NL | J70: X | K70: TDM | M70: EP260302 | N70: 5166247074 | R70: 1 | T70: 1PK/0.5KG | X70: DHL
A71: =ROW( ) -3 -> 68 | B71: =VLOOKUP(D71,DSKH!$A:$B,2,0) -> A-383 | C71: HÀ | D71: JV | E71: X | F71: 308291025950 | G71: B11 | H71: 46085 | I71: NL | J71: X | K71: TSN | M71: ROCKFALL-JVUS20260303 | O71: 217-07136894 | R71: 1 | T71: 24CT/227.3KG | X71: SCSC
A72: =ROW( ) -3 -> 69 | B72: =VLOOKUP(D72,DSKH!$A:$B,2,0) -> A-383 | C72: HÀ | D72: JV | E72: X | F72: 308292504940 | G72: H21 | H72: 46085 | I72: NL | J72: X | K72: TN | M72: JVVN-API-260304 | O72: SURVNS2603038S | R72: 1 | T72: 6PK/40.23KG | X72: CÁT LÁI | Y72: CHUNG BOOKING
A73: =ROW( ) -3 -> 70 | B73: =VLOOKUP(D73,DSKH!$A:$B,2,0) -> A-383 | C73: HÀ | D73: JV | E73: X | F73: 308292501000 | G73: B11 | H73: 46085 | I73: NL | J73: X | K73: TN | R73: 1 | T73: 103PK/584.98KG
A74: =ROW( ) -3 -> 71 | B74: =VLOOKUP(D74,DSKH!$A:$B,2,0) -> A-383 | C74: HÀ | D74: JV | E74: X | F74: 308295968060 | G74: B11 | H74: 46086 | I74: NL | J74: X | K74: TN | M74: JVVN-JVUS-FLEXI#20260305 | O74: 30089793 | Q74: 1 | T74: 85PK/7583KG | U74: TEMU7558094 | V74: 202611110419 | W74: 500 | X74: CÁT LÁI
A75: =ROW( ) -3 -> 72 | B75: =VLOOKUP(D75,DSKH!$A:$B,2,0) -> A-56 | C75: HÀ | D75: VINAMELT - TRANCY | E75: X | F75: 308295315660 | G75: E42 | H75: 46086 | I75: NL | J75: X | K75: CX | M75: VMT-IWSHK003-26 | O75: KMTCVN01102725 | P75: 1 | T75: 218CT/2479.67KG | U75: BEAU2313779 | V75: 202611108730 | W75: 250 | X75: CÁT LÁI
A76: =ROW( ) -3 -> 73 | B76: =VLOOKUP(D76,DSKH!$A:$B,2,0) -> A-494 | C76: HÀ | D76: CÔNG NGHIỆP TMC | E76: X | F76: 308294463800 | G76: B11 | H76: 46086 | I76: NL | J76: X | K76: BH | M76: 7 | S76: 1 | T76: 8PK/6941KG
A77: =ROW( ) -3 -> 74 | B77: =VLOOKUP(D77,DSKH!$A:$B,2,0) -> A-29 | C77: HÀ | D77: GIPT - DUMA | E77: X | F77: 308291298730 | G77: E62 | H77: 46085 | I77: NL | J77: X | K77: TN | M77: GGG260301 | O77: KMTCVN01104801 | P77: 1 | T77: 10PP/2782.8KG | U77: KMTU7494259 | V77: 202611100226 | W77: 250 | X77: CÁT LÁI
A78: =ROW( ) -3 -> 75 | B78: =VLOOKUP(D78,DSKH!$A:$B,2,0) -> A-29 | C78: HÀ | D78: GIPT - TQVĐ | E78: N | F78: 108020042430 | G78: E31 | H78: 46085 | I78: NL | J78: X | K78: TN | M78: FUT20260302 | N78: 5973714040 | R78: 1 | T78: 3PK/2.3KG | X78: DHL
A79: =ROW( ) -3 -> 76 | B79: =VLOOKUP(D79,DSKH!$A:$B,2,0) -> A-29 | C79: HÀ | D79: GIPT - TQVĐ | E79: N | F79: 108020161760 | G79: E31 | H79: 46085 | I79: NL | J79: X | K79: TN | M79: FUT20260301 | N79: 5973714084 | R79: 1 | T79: 1PK/4.6KG | X79: DHL
A80: =ROW( ) -3 -> 77 | B80: =VLOOKUP(D80,DSKH!$A:$B,2,0) -> A-29 | C80: HÀ | D80: GIPT - TQVĐ | E80: N | F80: 108024183300 | G80: E31 | H80: 46086 | I80: NL | J80: X | K80: TN | M80: GIPLK260301- HONENG ELECTRONICS | N80: 889094513840 | R80: 1 | T80: 1PK/7.6KG | X80: FEDEX
A81: =ROW( ) -3 -> 78 | B81: =VLOOKUP(D81,DSKH!$A:$B,2,0) -> A-29 | C81: HÀ | D81: GIPT - TQVĐ | E81: N | F81: 108024210120 | G81: E31 | H81: 46086 | I81: NL | J81: X | K81: TN | M81: SII-465672-465673 | N81: 889275235136 | R81: 1 | T81: 2PK/38KG | X81: FEDEX
A82: =ROW( ) -3 -> 79 | B82: =VLOOKUP(D82,DSKH!$A:$B,2,0) -> A-29 | C82: HÀ | D82: GIPT - TQVĐ | E82: N | F82: 108024243020 | G82: E31 | H82: 46086 | I82: NL | J82: X | K82: TN | M82: GIPLK260301- SEHWA | N82: 889192395329 | R82: 1 | T82: 1PK/3.5KG | X82: FEDEX
A83: =ROW( ) -3 -> 80 | B83: =VLOOKUP(D83,DSKH!$A:$B,2,0) -> A-29 | C83: HÀ | D83: GIPT - TQVĐ | E83: N | F83: 108024292500 | G83: E31 | H83: 46086 | I83: NL | J83: X | K83: TN | M83: GIPLK260301-EMANTECH | N83: 889234166290 | R83: 1 | T83: 3PK/1.5KG | X83: FEDEX
A84: =ROW( ) -3 -> 81 | B84: =VLOOKUP(D84,DSKH!$A:$B,2,0) -> B-57 | C84: HÀ | D84: HONGSEN - TQQT | E84: X | F84: 308295594960 | G84: B11 | H84: 46086 | I84: NL | J84: X | K84: TN | M84: 85 | S84: 1 | T84: 1264PK/5446.35KG
A85: =ROW( ) -3 -> 82 | B85: =VLOOKUP(D85,DSKH!$A:$B,2,0) -> B-57 | C85: HÀ | D85: HONGSEN - TQQT | E85: X | F85: 308291653740 | G85: B11 | H85: 46085 | I85: NL | J85: X | K85: TN | M85: 84 | S85: 1 | T85: 288PK/1676.18KG
A86: =ROW( ) -3 -> 83 | B86: =VLOOKUP(D86,DSKH!$A:$B,2,0) -> A-324 | C86: HÀ | D86: SCHAEFFLER | E86: X | F86: 308290728120 | G86: E62 | H86: 46085 | I86: NL | J86: X | K86: BH | M86: 6603067113+6603067114 | O86: SGNBKK158573V | R86: 1 | T86: 8PP/1546KG | V86: 266314287594 | W86: 23.19 | X86: CÁT LÁI
A87: =ROW( ) -3 -> 84 | B87: =VLOOKUP(D87,DSKH!$A:$B,2,0) -> A-324 | C87: HÀ | D87: SCHAEFFLER | E87: X | F87: 308290761500 | G87: E62 | H87: 46085 | I87: NL | J87: X | K87: BH | M87: 6603067116+6603067117+6603067119 | O87: SGNBKK158578V | R87: 1 | T87: 31PP/5140KG | V87: 266310726602 | W87: 77.1 | X87: CÁT LÁI | Y87: CHUNG BOOKING
A88: =ROW( ) -3 -> 85 | B88: =VLOOKUP(D88,DSKH!$A:$B,2,0) -> A-324 | C88: HÀ | D88: SCHAEFFLER | E88: X | F88: 308290758660 | G88: E62 | H88: 46085 | I88: NL | J88: X | K88: BH
A89: =ROW( ) -3 -> 86 | B89: =VLOOKUP(D89,DSKH!$A:$B,2,0) -> A-324 | C89: HÀ | D89: SCHAEFFLER | E89: X | F89: 308290789720 | G89: E62 | H89: 46085 | I89: NL | J89: X | K89: BH | M89: 6603067115 | O89: SGNBKK158579V | R89: 1 | T89: 3PP/741KG | X89: CÁT LÁI
A90: =ROW( ) -3 -> 87 | B90: =VLOOKUP(D90,DSKH!$A:$B,2,0) -> A-324 | C90: HÀ | D90: SCHAEFFLER | E90: X | F90: 308290832310 | G90: E62 | H90: 46085 | I90: NL | J90: X | K90: BH | M90: 6603067203+6603067118 | O90: SGNJKT158571V | R90: 1 | T90: 7PP/1025KG | V90: 266307762410 | W90: 15.375 | X90: CÁT LÁI
A91: =ROW( ) -3 -> 88 | B91: =VLOOKUP(D91,DSKH!$A:$B,2,0) -> A-408 | C91: HÀ | D91: FIRST METAL | E91: TIA | F91: 103897425330 | G91: G12 | H91: 46115 | I91: MM | M91: 47NF2624 | Y91: GIA HẠN TÁI XUẤT
A92: =ROW( ) -3 -> 89 | B92: =VLOOKUP(D92,DSKH!$A:$B,2,0) -> B-57 | C92: HÀ | D92: NEW-TQQT | E92: X | F92: 308296654800 | G92: E42 | H92: 46086 | I92: NL | J92: X | K92: CX | M92: NEW4328-1 | O92: SGNG36057700 | Q92: 1 | T92: 8PK/4379.02KG | U92: SEGU5969839 | X92: ĐỒNG NAI | Y92: CHUNG CONT
A93: =ROW( ) -3 -> 90 | B93: =VLOOKUP(D93,DSKH!$A:$B,2,0) -> B-57 | C93: HÀ | D93: NEW-TQQT | E93: X | F93: 308296639620 | G93: E42 | H93: 46086 | I93: NL | J93: X | K93: CX | M93: NEW4328-1 | T93: 34PK/15256.86KG
A94: =ROW( ) -3 -> 91 | B94: =VLOOKUP(D94,DSKH!$A:$B,2,0) -> A-29 | C94: HÀ | D94: GIPT - TQVĐ | E94: X | F94: 308301490950 | G94: E62 | H94: 46087 | I94: NL | J94: X | K94: TN | M94: FRW260301 | R94: 1 | T94: 40PP/14147.42KG | X94: KNQ
A95: =ROW( ) -3 -> 92 | B95: =VLOOKUP(D95,DSKH!$A:$B,2,0) -> A-29 | C95: HÀ | D95: GIPT - TQVĐ | E95: X | F95: 308301545330 | G95: E62 | H95: 46087 | I95: NL | J95: X | K95: TN | M95: PNX260301 | R95: 1 | T95: 1PP/193.19KG | X95: KNQ
A96: =ROW( ) -3 -> 93 | B96: =VLOOKUP(D96,DSKH!$A:$B,2,0) -> A-29 | C96: HÀ | D96: GIPT - TQVĐ | E96: X | F96: 308301589430 | G96: E62 | H96: 46087 | I96: NL | J96: X | K96: TN | M96: FRW260302 | R96: 1 | T96: 1PP/316.44KG | X96: KNQ
A97: =ROW( ) -3 -> 94 | B97: =VLOOKUP(D97,DSKH!$A:$B,2,0) -> A-383 | C97: HÀ | D97: JV | E97: X | F97: 308301883650 | G97: E62 | H97: 46087 | I97: NL | J97: X | K97: TN | M97: JV-PANARUB-20260306-A | O97: 1658946660 | R97: 1 | T97: 1CT/29.3KG | X97: DHL
A98: =ROW( ) -3 -> 95 | B98: =VLOOKUP(D98,DSKH!$A:$B,2,0) -> B-57 | C98: HÀ | D98: HONGSEN - TQQT | E98: X | F98: 308299212560 | G98: B11 | H98: 46087 | I98: NL | J98: X | K98: TN | M98: 86 | S98: 1 | T98: 1200PK/10092KG
A99: =ROW( ) -3 -> 96 | B99: =VLOOKUP(D99,DSKH!$A:$B,2,0) -> A-37 | C99: THANH | D99: FLEMING | E99: X | F99: 308283596040 | G99: E42 | H99: 46083 | I99: NL | J99: X | K99: CX | M99: AH-2511043-047-062 | R99: 1 | T99: 972k/5.442,12kg/12.546 | V99: 0 | X99: CFS KHO 6
A100: =ROW( ) -3 -> 97 | B100: =VLOOKUP(D100,DSKH!$A:$B,2,0) -> A-37 | C100: THANH | D100: FLEMING | E100: X | F100: 308286636840 | G100: E42 | H100: 46083 | I100: NL | J100: X | K100: CX | M100: MAX-2512108-0013-1052 | Q100: 1 | T100: 2170k?13.017,2kg/25.99 | U100: MRSU5860280 | V100: 0 | X100: BÌNH DƯƠNG
A101: =ROW( ) -3 -> 98 | B101: =VLOOKUP(D101,DSKH!$A:$B,2,0) -> A-324 | C101: THANH | D101: SCHAEFFLER | E101: X | F101: 308287253540 | G101: E62 | H101: 46084 | I101: NL | J101: X | K101: BH | M101: 6603066951+6603066992+6603066993 | R101: 1 | T101: 28k/5.268kg | V101: 0 | X101: TCS
...

Sheet THÁNG 4_Tổng hợp
A1: STT | B1: MÃ KHÁCH HÀNG | C1: NHÂN VIÊN | D1: KHÁCH HÀNG | E1: CÔNG VIỆC | F1: SỐ TỜ KHAI | G1: LOẠI HÌNH | H1: NGÀY TỜ KHAI | I1: LOẠI HÀNG | J1: LUỒNG TK | K1: HẢI QUAN | L1: C/O | M1: SỐ INV/VAT | N1: SỐ BILL | O1: SỐ BOOKING | P1: SỐ LƯỢNG | T1: (KIỆN, KG) | U1: SỐ CONTAINER | V1: THÔNG BÁO PHÍ CSHT | W1: SỐ TIỀN CSHT | X1: CẢNG XUẤT - CẢNG NHẬP | Y1: GHI CHÚ
P2: 20' | Q2: 40' | R2: LCL | S2: TC
A4: =ROW( ) -3 -> 1 | B4: =VLOOKUP(D4,DSKH!$A:$B,2,0) -> A-42 | C4: MY | D4: SHIN FUNG | E4: X | F4: 308390237540 | G4: B11 | H4: 46113 | I4: NL | J4: X | K4: TN | M4: 142026-BILBAO | O4: SGNE31757700 | P4: 1 | T4: 24K/13.942,7KG | U4: BSIU2789512 | V4: 202611323384 | W4: 250000 | X4: CÁT LÁI | Y4: CHUNG LÔ
A5: =ROW( ) -3 -> 2 | B5: =VLOOKUP(D5,DSKH!$A:$B,2,0) -> A-42 | C5: MY | D5: SHIN FUNG | E5: X | F5: 308390246200 | G5: B11 | H5: 46113 | I5: NL | J5: X | K5: TN
A6: =ROW( ) -3 -> 3 | B6: =VLOOKUP(D6,DSKH!$A:$B,2,0) -> A-144 | C6: MY | D6: JINGGUANG | E6: N | F6: 108110105940 | G6: E15 | H6: 46113 | I6: NL | J6: X | K6: CX | M6: 286 | S6: 1 | T6: 1K/62KG
A7: =ROW( ) -3 -> 4 | B7: =VLOOKUP(D7,DSKH!$A:$B,2,0) -> A-144 | C7: MY | D7: JINGGUANG | E7: N | F7: 108110101300 | G7: E15 | H7: 46113 | I7: NL | J7: X | K7: CX | M7: 281 | S7: 1 | T7: 27K/674,196KG
A8: =ROW( ) -3 -> 5 | B8: =VLOOKUP(D8,DSKH!$A:$B,2,0) -> A-144 | C8: MY | D8: JINGGUANG | E8: N | F8: 108110075840 | G8: E15 | H8: 46113 | I8: NL | J8: X | K8: CX | M8: 138 | S8: 1 | T8: 3K/15KG
A9: =ROW( ) -3 -> 6 | B9: =VLOOKUP(D9,DSKH!$A:$B,2,0) -> A-144 | C9: MY | D9: JINGGUANG | E9: N | F9: 108109842960 | G9: E15 | H9: 46113 | I9: NL | J9: X | K9: CX | M9: 749 | S9: 1 | T9: 53K/899,08KG
A10: =ROW( ) -3 -> 7 | B10: =VLOOKUP(D10,DSKH!$A:$B,2,0) -> A-144 | C10: MY | D10: JINGGUANG | E10: N | F10: 108108168930 | G10: E13 | H10: 46113 | I10: NL | J10: V | K10: CX | M10: 12 | S10: 1 | T10: 1K/1.413KG
A11: =ROW( ) -3 -> 8 | B11: =VLOOKUP(D11,DSKH!$A:$B,2,0) -> A-144 | C11: MY | D11: JINGGUANG | E11: X | F11: 308389848010 | G11: E42 | H11: 46113 | I11: NL | J11: X | K11: CX | M11: JG-XN2-20260401 | S11: 1 | T11: 474K/4.674,568KG
A12: =ROW( ) -3 -> 9 | B12: =VLOOKUP(D12,DSKH!$A:$B,2,0) -> A-144 | C12: MY | D12: JINGGUANG | E12: X | F12: 308389657020 | G12: E42 | H12: 46113 | I12: NL | J12: X | K12: CX | M12: 326 | S12: 1 | T12: 232K/11.538,69KG
A13: =ROW( ) -3 -> 10 | B13: =VLOOKUP(D13,DSKH!$A:$B,2,0) -> A-144 | C13: MY | D13: JINGGUANG | E13: X | F13: 308388495940 | G13: E42 | H13: 46113 | I13: NL | J13: X | K13: CX | M13: 325 | S13: 1 | T13: 74K/6.660KG
A14: =ROW( ) -3 -> 11 | B14: =VLOOKUP(D14,DSKH!$A:$B,2,0) -> A-144 | C14: MY | D14: JINGGUANG | E14: X | F14: 308388280930 | G14: E42 | H14: 46113 | I14: NL | J14: X | K14: CX | M14: 324 | S14: 1 | T14: 128K/11.325,13KG
A15: =ROW( ) -3 -> 12 | B15: =VLOOKUP(D15,DSKH!$A:$B,2,0) -> A-144 | C15: MY | D15: JINGGUANG | E15: X | F15: 308388236130 | G15: E42 | H15: 46113 | I15: NL | J15: V | K15: CX | M15: 323 | S15: 1 | T15: 217K/2.513,54KG
A16: =ROW( ) -3 -> 13 | B16: =VLOOKUP(D16,DSKH!$A:$B,2,0) -> A-144 | C16: MY | D16: JINGGUANG | E16: X | F16: 308388185250 | G16: E42 | H16: 46113 | I16: NL | J16: X | K16: CX | M16: 322 | S16: 1 | T16: 29K/358,66KG
A17: =ROW( ) -3 -> 14 | B17: =VLOOKUP(D17,DSKH!$A:$B,2,0) -> A-144 | C17: MY | D17: JINGGUANG | E17: X | F17: 308388030440 | G17: E42 | H17: 46113 | I17: NL | J17: X | K17: CX | M17: 321 | S17: 1 | T17: 415K/6.325,3KG
A18: =ROW( ) -3 -> 15 | B18: =VLOOKUP(D18,DSKH!$A:$B,2,0) -> A-144 | C18: MY | D18: JINGGUANG | E18: X | F18: 308387729220 | G18: E42 | H18: 46113 | I18: NL | J18: X | K18: CX | M18: JG-XN5-20260401 | S18: 1 | T18: 2K/60,352KG
A19: =ROW( ) -3 -> 16 | B19: =VLOOKUP(D19,DSKH!$A:$B,2,0) -> A-57 | C19: MY | D19: OT MOTOR | E19: N | F19: 108112222520 | G19: E13 | H19: 46114 | I19: NL | J19: X | K19: NT | M19: I-260251 | N19: 8701 9759 1377 | R19: 1 | T19: 1K/0,3KG
A20: =ROW( ) -3 -> 17 | B20: =VLOOKUP(D20,DSKH!$A:$B,2,0) -> A-56 | C20: MY | D20: NHẬT VIỆT - TRANCY | E20: X | F20: 308392330650 | G20: B11 | H20: 46114 | I20: NL | J20: X | K20: DN1 | M20: NVC-26/04-01 | O20: MPSHA2604071 | R20: 1 | T20: 1K/77,53KG | X20: KHO CÁT LÁI
A21: =ROW( ) -3 -> 18 | B21: =VLOOKUP(D21,DSKH!$A:$B,2,0) -> A-144 | C21: MY | D21: JINGGUANG | E21: X | F21: 308392137930 | G21: E42 | H21: 46114 | I21: NL | J21: X | K21: CX | M21: 327 | S21: 1 | T21: 1K/16,5KG
A22: =ROW( ) -3 -> 19 | B22: =VLOOKUP(D22,DSKH!$A:$B,2,0) -> A-144 | C22: MY | D22: JINGGUANG | E22: X | F22: 308392185200 | G22: E42 | H22: 46114 | I22: NL | J22: X | K22: CX | M22: 328 | S22: 1 | T22: 18K/1.504,54KG
A23: =ROW( ) -3 -> 20 | B23: =VLOOKUP(D23,DSKH!$A:$B,2,0) -> A-144 | C23: MY | D23: JINGGUANG | E23: X | F23: 308393100430 | G23: E42 | H23: 46114 | I23: NL | J23: X | K23: CX | M23: 329 | S23: 1 | T23: 104K/28.869KG
A24: =ROW( ) -3 -> 21 | B24: =VLOOKUP(D24,DSKH!$A:$B,2,0) -> A-144 | C24: MY | D24: JINGGUANG | E24: X | F24: 308393228420 | G24: E42 | H24: 46114 | I24: NL | J24: X | K24: CX | M24: 330 | S24: 1 | T24: 92K/18.265,68KG
A25: =ROW( ) -3 -> 22 | B25: =VLOOKUP(D25,DSKH!$A:$B,2,0) -> A-144 | C25: MY | D25: JINGGUANG | E25: X | F25: 308393475040 | G25: E42 | H25: 46114 | I25: NL | J25: X | K25: CX | M25: 331 | S25: 1 | T25: 280K/22.313,08KG
A26: =ROW( ) -3 -> 23 | B26: =VLOOKUP(D26,DSKH!$A:$B,2,0) -> A-144 | C26: MY | D26: JINGGUANG | E26: X | F26: 308393627860 | G26: E42 | H26: 46114 | I26: NL | J26: X | K26: CX | M26: 332 | S26: 1 | T26: 153K/12.535,2KG
A27: =ROW( ) -3 -> 24 | B27: =VLOOKUP(D27,DSKH!$A:$B,2,0) -> A-144 | C27: MY | D27: JINGGUANG | E27: X | F27: 308393682940 | G27: E42 | H27: 46114 | I27: NL | J27: X | K27: CX | M27: 333 | S27: 1 | T27: 146K/12.940,71KG
A28: =ROW( ) -3 -> 25 | B28: =VLOOKUP(D28,DSKH!$A:$B,2,0) -> A-144 | C28: MY | D28: JINGGUANG | E28: X | F28: 308393858860 | G28: E42 | H28: 46114 | I28: NL | J28: X | K28: CX | M28: 334 | S28: 1 | T28: 176K/11.585,04KG
A29: =ROW( ) -3 -> 26 | B29: =VLOOKUP(D29,DSKH!$A:$B,2,0) -> A-144 | C29: MY | D29: JINGGUANG | E29: N | F29: 108110126940 | G29: E15 | H29: 46114 | I29: NL | J29: X | K29: CX | M29: 350 | S29: 1 | T29: 112CT/252,58KG
A30: =ROW( ) -3 -> 27 | B30: =VLOOKUP(D30,DSKH!$A:$B,2,0) -> A-212 | C30: MY | D30: LEADER | E30: N | F30: 108118278660 | G30: E15 | H30: 46115 | I30: NL | J30: X | K30: TN | M30: 475 | S30: 1 | T30: 1.483K/29,202,42
A31: =ROW( ) -3 -> 28 | B31: =VLOOKUP(D31,DSKH!$A:$B,2,0) -> A-212 | C31: MY | D31: LEADER | E31: N | F31: 108118292330 | G31: E15 | H31: 46115 | I31: NL | J31: X | K31: TN | M31: 476 | S31: 1 | T31: 1.296K/27.027,98KG
A32: =ROW( ) -3 -> 29 | B32: =VLOOKUP(D32,DSKH!$A:$B,2,0) -> A-502 | C32: HUYỀN | D32: RYDER | E32: N | F32: 108105128350 | G32: E31 | H32: 46113 | I32: NL | J32: X | K32: DN3 | M32: 20260331-RIL-522 | N32: 889981937522 | R32: 1
A33: =ROW( ) -3 -> 30 | B33: =VLOOKUP(D33,DSKH!$A:$B,2,0) -> A-502 | C33: HUYỀN | D33: RYDER | E33: N | F33: 108105891940 | G33: E31 | H33: 46113 | I33: NL | J33: X | K33: DN3 | M33: C013102603001 | N33: 280326PL2026036032 | R33: 1 | T33: 3PP/1.446KG | V33: 202611327989 | W33: 21690
A34: =ROW( ) -3 -> 31 | B34: =VLOOKUP(D34,DSKH!$A:$B,2,0) -> A-502 | C34: HUYỀN | D34: RYDER | E34: N | F34: 108107653400 | G34: E31 | H34: 46113 | I34: NL | J34: V | K34: DN3 | M34: M20260326-RIL | N34: HKGHCM26030132 | Q34: 1 | U34: SEGU5539503 | V34: 202611328049 | W34: 500000 | X34: CAT LAI | Y34: CHUNG LÔ
A35: =ROW( ) -3 -> 32 | B35: =VLOOKUP(D35,DSKH!$A:$B,2,0) -> A-502 | C35: HUYỀN | D35: RYDER | E35: N | F35: 108107703210 | G35: E31 | H35: 46113 | I35: NL | J35: X | K35: DN3 | M35: M20260326-RIL
A36: =ROW( ) -3 -> 33 | B36: =VLOOKUP(D36,DSKH!$A:$B,2,0) -> A-502 | C36: HUYỀN | D36: RYDER | E36: N | F36: 108107724100 | G36: E31 | H36: 46113 | I36: NL | J36: X | K36: DN3 | M36: M20260326-SZ
A37: =ROW( ) -3 -> 34 | B37: =VLOOKUP(D37,DSKH!$A:$B,2,0) -> A-502 | C37: HUYỀN | D37: RYDER | E37: N | F37: 108107758360 | G37: E31 | H37: 46113 | I37: NL | J37: V | K37: DN3 | M37: M20260326-SZ
A38: =ROW( ) -3 -> 35 | B38: =VLOOKUP(D38,DSKH!$A:$B,2,0) -> A-502 | C38: HUYỀN | D38: RYDER | E38: N | F38: 108108662540 | G38: E31 | H38: 46113 | I38: NL | J38: X | K38: DN3 | M38: M20260326-XF
A39: =ROW( ) -3 -> 36 | B39: =VLOOKUP(D39,DSKH!$A:$B,2,0) -> A-502 | C39: HUYỀN | D39: RYDER | E39: N | F39: 108108665560 | G39: E31 | H39: 46113 | I39: NL | J39: X | K39: DN3 | M39: M20260326-XF
A40: =ROW( ) -3 -> 37 | B40: =VLOOKUP(D40,DSKH!$A:$B,2,0) -> A-502 | C40: HUYỀN | D40: RYDER | E40: X | F40: 308386687400 | G40: E62 | H40: 46113 | I40: NL | J40: X | K40: DN3 | M40: RD260401-GROOVE-DK | O40: SGNCPH159333V | R40: 1 | T40: 2PP/531.96KG | X40: CAT LAI KHO 1
A41: =ROW( ) -3 -> 38 | B41: =VLOOKUP(D41,DSKH!$A:$B,2,0) -> A-502 | C41: HUYỀN | D41: RYDER | E41: X | F41: 308389790830 | G41: E62 | H41: 46114 | I41: NL | J41: X | K41: DN3 | M41: RD260401-AGUILAR-FI | O41: 26019110 | R41: 1 | T41: 8PP/1543.95KG | V41: 202611323466 | W41: 23160 | X41: CAT LAI KHO 5
A42: =ROW( ) -3 -> 39 | B42: =VLOOKUP(D42,DSKH!$A:$B,2,0) -> A-502 | C42: HUYỀN | D42: RYDER | E42: X | F42: 308390006320 | G42: E62 | H42: 46114 | I42: NL | J42: X | K42: DN3 | M42: RD260402-GROOVE-DK | R42: 1 | T42: 2PP/373.52KG | X42: SCSC
A43: =ROW( ) -3 -> 40 | B43: =VLOOKUP(D43,DSKH!$A:$B,2,0) -> A-502 | C43: HUYỀN | D43: RYDER | E43: N | F43: 108110010960 | G43: E31 | H43: 46114 | I43: NL | J43: V | K43: DN3 | M43: VN260331XF-FEDEX-N | N43: 412669259170 | R43: 1 | T43: 2CT/10.3KG
A44: =ROW( ) -3 -> 41 | B44: =VLOOKUP(D44,DSKH!$A:$B,2,0) -> A-502 | C44: HUYỀN | D44: RYDER | E44: N | F44: 108111643140 | G44: E31 | H44: 46114 | I44: NL | J44: X | K44: DN3 | M44: 123363-123364 | N44: DFS029053016 | R44: 1 | T44: 7BX/87.5KG | X44: CL-KHO 2
A45: =ROW( ) -3 -> 42 | B45: =VLOOKUP(D45,DSKH!$A:$B,2,0) -> A-12 | C45: MINH | D45: MATSUYA | E45: X | F45: 308389038220 | G45: E42 | H45: 46113 | I45: NL | J45: XANH | K45: TN | M45: 186 | S45: 1 | T45: 32K/10.560,92KG
A46: =ROW( ) -3 -> 43 | B46: =VLOOKUP(D46,DSKH!$A:$B,2,0) -> A-12 | C46: MINH | D46: MATSUYA | E46: X | F46: 308389470010 | G46: E42 | H46: 46113 | I46: NL | J46: XANH | K46: TN | M46: 188 | S46: 1 | T46: 3K/531,65KG
A47: =ROW( ) -3 -> 44 | B47: =VLOOKUP(D47,DSKH!$A:$B,2,0) -> A-12 | C47: MINH | D47: MATSUYA | E47: X | F47: 308393103820 | H47: 46114 | I47: NL | J47: XANH | K47: TN | M47: 190 | S47: 1 | T47: 32K/11,185.53KG
A48: =ROW( ) -3 -> 45 | B48: =VLOOKUP(D48,DSKH!$A:$B,2,0) -> A-12 | C48: MINH | D48: MATSUYA | E48: X | F48: 308396875530 | H48: 46115 | I48: NL | J48: XANH | K48: TN | M48: 193 | S48: 1 | T48: 28K/8.663,96KG
A49: =ROW( ) -3 -> 46 | B49: =VLOOKUP(D49,DSKH!$A:$B,2,0) -> A-263 | C49: HOÀNG YẾN | D49: HOME CMC | E49: X | F49: 308387785810 | G49: E42 | H49: 46113 | I49: NL | J49: X | K49: NT | M49: 26M-P010482 | O49: 339IVN0039068 | Q49: 1 | T49: 861PK/6.543,6KG | U49: TRHU8603165 | V49: 202611315526 | W49: 500000 | X49: CANG CAT LAI
A50: =ROW( ) -3 -> 47 | B50: =VLOOKUP(D50,DSKH!$A:$B,2,0) -> A-212 | C50: HOÀNG YẾN | D50: LEADER | E50: N | F50: 108113647830 | G50: E11 | H50: 46114 | I50: NL | J50: X | K50: TN | M50: FJYN0612 | N50: SITGNBCLD519826 | Q50: 6 | T50: 3640PK/97500.700KG | U50: FFAU7032872 FFAU7067837 HPCU5046885 TCKU7966487 TGCU5269650 TIIU5187537 | X50: CANG CAT LAI | Y50: TK CHUNG CONT
A51: =ROW( ) -3 -> 48 | B51: =VLOOKUP(D51,DSKH!$A:$B,2,0) -> A-212 | C51: HOÀNG YẾN | D51: LEADER | E51: N | F51: 108113638250 | G51: E11 | H51: 46114 | I51: NL | J51: X | K51: TN
A52: =ROW( ) -3 -> 49 | B52: =VLOOKUP(D52,DSKH!$A:$B,2,0) -> A-212 | C52: HOÀNG YẾN | D52: LEADER | E52: N | F52: 108113613750 | G52: E11 | H52: 46114 | I52: NL | J52: X | K52: TN
A53: =ROW( ) -3 -> 50 | B53: =VLOOKUP(D53,DSKH!$A:$B,2,0) -> A-212 | C53: HOÀNG YẾN | D53: LEADER | E53: N | F53: 108113602920 | G53: E11 | H53: 46114 | I53: NL | J53: X | K53: TN
A54: =ROW( ) -3 -> 51 | B54: =VLOOKUP(D54,DSKH!$A:$B,2,0) -> A-212 | C54: HOÀNG YẾN | D54: LEADER | E54: N | F54: 108113595550 | G54: E11 | H54: 46114 | I54: NL | J54: X | K54: TN
A55: =ROW( ) -3 -> 52 | B55: =VLOOKUP(D55,DSKH!$A:$B,2,0) -> A-212 | C55: HOÀNG YẾN | D55: LEADER | E55: N | F55: 108113590760 | G55: E11 | H55: 46114 | I55: NL | J55: X | K55: TN
A56: =ROW( ) -3 -> 53 | B56: =VLOOKUP(D56,DSKH!$A:$B,2,0) -> A-212 | C56: HOÀNG YẾN | D56: LEADER | E56: N | F56: 108113584020 | G56: E11 | H56: 46114 | I56: NL | J56: X | K56: TN
A57: =ROW( ) -3 -> 54 | B57: =VLOOKUP(D57,DSKH!$A:$B,2,0) -> A-212 | C57: HOÀNG YẾN | D57: LEADER | E57: N | F57: 108113529050 | G57: E11 | H57: 46114 | I57: NL | J57: X | K57: TN
A58: =ROW( ) -3 -> 55 | B58: =VLOOKUP(D58,DSKH!$A:$B,2,0) -> A-212 | C58: HOÀNG YẾN | D58: LEADER | E58: N | F58: 108113500020 | G58: E11 | H58: 46114 | I58: NL | J58: X | K58: TN
A59: =ROW( ) -3 -> 56 | B59: =VLOOKUP(D59,DSKH!$A:$B,2,0) -> A-212 | C59: HOÀNG YẾN | D59: LEADER | E59: N | F59: 108113474230 | G59: E11 | H59: 46114 | I59: NL | J59: X | K59: TN
A60: =ROW( ) -3 -> 57 | B60: =VLOOKUP(D60,DSKH!$A:$B,2,0) -> A-212 | C60: HOÀNG YẾN | D60: LEADER | E60: N | F60: 108113452900 | G60: E11 | H60: 46114 | I60: NL | J60: X | K60: TN
A61: =ROW( ) -3 -> 58 | B61: =VLOOKUP(D61,DSKH!$A:$B,2,0) -> A-212 | C61: HOÀNG YẾN | D61: LEADER | E61: N | F61: 108113423500 | G61: E11 | H61: 46114 | I61: NL | J61: X | K61: TN
A62: =ROW( ) -3 -> 59 | B62: =VLOOKUP(D62,DSKH!$A:$B,2,0) -> A-212 | C62: HOÀNG YẾN | D62: LEADER | E62: N | F62: 108113387760 | G62: E11 | H62: 46114 | I62: NL | J62: X | K62: TN
... A95: =ROW( ) -3 -> 92 | B95: =VLOOKUP(D95,DSKH!$A:$B,2,0) -> A-212 | C95: HOÀNG YẾN | D95: LEADER | E95: N | F95: 108112463760 | G95: E11 | H95: 46114 | I95: NL | J95: X | K95: TN
A96: =ROW( ) -3 -> 93 | B96: =VLOOKUP(D96,DSKH!$A:$B,2,0) -> A-263 | C96: HOÀNG YẾN | D96: HOME CMC | E96: X | F96: 308391760630 | G96: E42 | H96: 46114 | I96: NL | J96: X | K96: NT | M96: 26M-P010505 | O96: SGN3099192 | Q96: 1 | T96: 861PK/6.543,6KG | U96: BMOU4939175 | X96: CANG CAT LAI
A97: =ROW( ) -3 -> 94 | B97: =VLOOKUP(D97,DSKH!$A:$B,2,0) -> A-263 | C97: HOÀNG YẾN | D97: HOME CMC | E97: X | F97: 308391806350 | G97: E42 | H97: 46114 | I97: NL | J97: X | K97: NT | M97: 26M-P010580 | O97: 6447022390 | Q97: 1 | T97: 902PK/7.486,6KG | U97: TGBU8717293 | X97: CANG CAT LAI
A98: =ROW( ) -3 -> 95 | B98: =VLOOKUP(D98,DSKH!$A:$B,2,0) -> A-595 | C98: HOÀNG YẾN | D98: TECAN | E98: N | F98: 108113331760 | G98: E31 | H98: 46114 | I98: NL | J98: X | K98: MP | M98: 9048875-00 | N98: I590135 | R98: 1 | T98: 4PK/46,7KG | X98: KHO TCS
A99: =ROW( ) -3 -> 96 | B99: =VLOOKUP(D99,DSKH!$A:$B,2,0) -> A-595 | C99: HOÀNG YẾN | D99: TECAN | E99: N | F99: 108111373310 | G99: E31 | H99: 46114 | I99: NL | J99: X | K99: MP | M99: 20269829 | N99: 7297442810 | R99: 1 | T99: 1PK/2,4KG | X99: KHO DHL
A100: =ROW( ) -3 -> 97 | B100: =VLOOKUP(D100,DSKH!$A:$B,2,0) -> A-590 | C100: HOÀNG | D100: YUEDA | E100: N | F100: 108106057730 | G100: E15 | H100: 46113 | I100: NL | J100: X | K100: TN | M100: 310 | S100: 1 | T100: 10K/342.33KG
A101: =ROW( ) -3 -> 98 | B101: =VLOOKUP(D101,DSKH!$A:$B,2,0) -> A-590 | C101: HOÀNG | D101: YUEDA | E101: N | F101: 108106086060 | G101: E15 | H101: 46113 | I101: NL | J101: X | K101: TN | M101: 382 | S101: 1 | T101: 3531K/30298.64KG
A102: =ROW( ) -3 -> 99 | B102: =VLOOKUP(D102,DSKH!$A:$B,2,0) -> A-590 | C102: HOÀNG | D102: YUEDA | E102: N | F102: 108106222120 | G102: E15 | H102: 46113 | I102: NL | J102: V | K102: TN | M102: 128 | S102: 1 | T102: 38K/38956KG
A103: =ROW( ) -3 -> 100 | B103: =VLOOKUP(D103,DSKH!$A:$B,2,0) -> A-590 | C103: HOÀNG | D103: YUEDA | E103: X | F103: 308387588150 | G103: E42 | H103: 46113 | I103: NL | J103: X | K103: TN | M103: EX260331 | R103: 1 | T103: 5K/65KG | X103: KHO FEDEX
A104: =ROW( ) -3 -> 101 | B104: =VLOOKUP(D104,DSKH!$A:$B,2,0) -> A-590 | C104: HOÀNG | D104: YUEDA | E104: N | F104: 108107250750 | G104: E11 | H104: 46113 | I104: NL | J104: X | K104: TN | M104: YUEDA20260329 | N104: 018-92418465 | R104: 1 | T104: 14K/210KG | X104: KHO TCS
A105: =ROW( ) -3 -> 102 | B105: =VLOOKUP(D105,DSKH!$A:$B,2,0) -> A-590 | C105: HOÀNG | D105: YUEDA | E105: N | F105: 108108978350 | G105: E15 | H105: 46113 | I105: NL | J105: X | K105: TN | M105: 42 | S105: 1 | T105: 369K/98158.38KG
A106: =ROW( ) -3 -> 103 | B106: =VLOOKUP(D106,DSKH!$A:$B,2,0) -> A-590 | C106: HOÀNG | D106: YUEDA | E106: N | F106: 108109300610 | G106: E15 | H106: 46113 | I106: NL | J106: X | K106: TN | M106: 1029 | S106: 1 | T106: 69K/542.8KG
A107: =ROW( ) -3 -> 104 | B107: =VLOOKUP(D107,DSKH!$A:$B,2,0) -> A-590 | C107: HOÀNG | D107: YUEDA | E107: N | F107: 108109460910 | G107: E15 | H107: 46113 | I107: NL | J107: X | K107: TN | M107: 48 | S107: 1 | T107: 531K/1550.65KG
A108: =ROW( ) -3 -> 105 | B108: =VLOOKUP(D108,DSKH!$A:$B,2,0) -> A-590 | C108: HOÀNG | D108: YUEDA | E108: N | F108: 108109633810 | G108: E15 | H108: 46113 | I108: NL | J108: X | K108: TN | M108: 178 | S108: 1 | T108: 497K/3423.07KG
A109: =ROW( ) -3 -> 106 | B109: =VLOOKUP(D109,DSKH!$A:$B,2,0) -> A-590 | C109: HOÀNG | D109: YUEDA | E109: N | F109: 108109864220 | G109: E15 | H109: 46113 | I109: NL | J109: X | K109: TN | M109: 1049 | S109: 1 | T109: 39K/306.8KG
A110: =ROW( ) -3 -> 107 | B110: =VLOOKUP(D110,DSKH!$A:$B,2,0) -> A-472 | C110: HOÀNG | D110: YOSUN | E110: X | F110: 308387077260 | G110: B11 | H110: 46113 | I110: NL | J110: X | K110: CL | M110: YSVN20260330-01 | O110: 6446491520 | Q110: 2 | T110: 2132K/26329KG | U110: OOCU9212320 OOCU9698228 | V110: 202611314421 | W110: 1000000 | X110: CAT LAI
A111: =ROW( ) -3 -> 108 | B111: =VLOOKUP(D111,DSKH!$A:$B,2,0) -> A-472 | C111: HOÀNG | D111: YOSUN | E111: X | F111: 308387139450 | G111: B11 | H111: 46113 | I111: NL | J111: X | K111: CL | M111: YSVN20260330 | O111: 6446544290 | Q111: 4 | T111: 4600K/45064KG | U111: FCIU9824032 OOCU4848984 OOCU6437473 OOCU4855915 | V111: 202611314449 | W111: 2000000 | X111: CAT LAI
A112: =ROW( ) -3 -> 109 | B112: =VLOOKUP(D112,DSKH!$A:$B,2,0) -> A-472 | C112: HOÀNG | D112: YOSUN | E112: X | F112: 308387314010 | G112: B11 | H112: 46113 | I112: NL | J112: X | K112: TDM | M112: YSVN20260401 | O112: S3Z2266985 | R112: 1 | T112: 500K/2600KG | X112: KHO TBS
A113: =ROW( ) -3 -> 110 | B113: =VLOOKUP(D113,DSKH!$A:$B,2,0) -> A-472 | C113: HOÀNG | D113: YOSUN | E113: X | F113: 308387391340 | G113: B11 | H113: 46113 | I113: NL | J113: X | K113: TDM | M113: YSVN20260401-01 | O113: S3Z2267007 | R113: 1 | T113: 500K/2600KG | X113: KHO TBS
A114: =ROW( ) -3 -> 111 | B114: =VLOOKUP(D114,DSKH!$A:$B,2,0) -> A-09 | C114: HOÀNG | D114: JAAN-E | E114: X | F114: 308390294610 | G114: B11 | H114: 46113 | I114: NL | J114: X | K114: TN | M114: IN01042026 | O114: KEE26040410 | R114: 1 | T114: 4K/2,895.98KG | V114: 202611322318 | W114: 43440 | X114: KHO CAT LAI
A115: =ROW( ) -3 -> 112 | B115: =VLOOKUP(D115,DSKH!$A:$B,2,0) -> A-365 | C115: HOÀNG | D115: CHANGHONG | E115: N | F115: 108113541910 | G115: E13 | H115: 46114 | I115: MM | J115: V | K115: TN | M115: 83 | S115: 1 | T115: 1K/450KG
A116: =ROW( ) -3 -> 113 | B116: =VLOOKUP(D116,DSKH!$A:$B,2,0) -> A-211 | C116: HOÀNG | D116: TATA | E116: N | F116: 108110470200 | G116: E15 | H116: 46114 | I116: NL | J116: V | K116: TN | M116: 618 | S116: 1 | T116: 29K/276.37KG
A117: =ROW( ) -3 -> 114 | B117: =VLOOKUP(D117,DSKH!$A:$B,2,0) -> A-211 | C117: HOÀNG | D117: TATA | E117: N | F117: 108110681820 | G117: E15 | H117: 46114 | I117: NL | J117: X | K117: TN | M117: 421 | S117: 1 | T117: 19K/324.14KG
A118: =ROW( ) -3 -> 115 | B118: =VLOOKUP(D118,DSKH!$A:$B,2,0) -> A-211 | C118: HOÀNG | D118: TATA | E118: N | F118: 108110992250 | G118: E15 | H118: 46114 | I118: NL | J118: X | K118: TN | M118: 945 | S118: 1 | T118: 1375K/4407.92KG
A119: =ROW( ) -3 -> 116 | B119: =VLOOKUP(D119,DSKH!$A:$B,2,0) -> A-211 | C119: HOÀNG | D119: TATA | E119: N | F119: 108110790100 | G119: E15 | H119: 46114 | I119: NL | J119: X | K119: TN | M119: 946 | S119: 1 | T119: 136K/1091.48KG
A120: =ROW( ) -3 -> 117 | B120: =VLOOKUP(D120,DSKH!$A:$B,2,0) -> A-211 | C120: HOÀNG | D120: TATA | E120: X | F120: 308392460150 | G120: H21 | H120: 46114 | I120: NL | J120: X | K120: TN | M120: EMSON2026040201 | R120: 1 | T120: 1K/0.6KG | X120: KHO UPS
A121: =ROW( ) -3 -> 118 | B121: =VLOOKUP(D121,DSKH!$A:$B,2,0) -> A-590 | C121: HOÀNG | D121: YUEDA | E121: N | F121: 108112057100 | G121: E15 | H121: 46114 | I121: NL | J121: X | K121: TN | M121: 36 | S121: 1 | T121: 232K/6509.43KG
A122: =ROW( ) -3 -> 119 | B122: =VLOOKUP(D122,DSKH!$A:$B,2,0) -> A-590 | C122: HOÀNG | D122: YUEDA | E122: N | F122: 108111838440 | G122: E15 | H122: 46114 | I122: NL | J122: X | K122: TN | M122: 1546 | S122: 1 | T122: 117K/1113.64KG
A123: =ROW( ) -3 -> 120 | B123: =VLOOKUP(D123,DSKH!$A:$B,2,0) -> A-590 | C123: HOÀNG | D123: YUEDA | E123: X | F123: 308393040010 | G123: E42 | H123: 46114 | I123: NL | J123: X | K123: TN | M123: EX260402-1 | R123: 1 | T123: 1K/11KG | X123: KHO FEDEX
A124: =ROW( ) -3 -> 121 | B124: =VLOOKUP(D124,DSKH!$A:$B,2,0) -> A-590 | C124: HOÀNG | D124: YUEDA | E124: X | F124: 308393199940 | G124: E42 | H124: 46114 | I124: NL | J124: X | K124: TN | M124: EX260402 | R124: 1 | T124: 1K/13KG | X124: KHO FEDEX
A125: =ROW( ) -3 -> 122 | B125: =VLOOKUP(D125,DSKH!$A:$B,2,0) -> A-590 | C125: HOÀNG | D125: YUEDA | E125: X | F125: 308393371440 | G125: B11 | H125: 46114 | I125: NL | J125: V | K125: TN | M125: 314 | Y125: KHÔNG KHAI TK
A126: =ROW( ) -3 -> 123 | B126: =VLOOKUP(D126,DSKH!$A:$B,2,0) -> A-590 | C126: HOÀNG | D126: YUEDA | E126: N | F126: 108113253840 | G126: E15 | H126: 46114 | I126: NL | J126: X | K126: TN | M126: 942 | S126: 1 | T126: 2019K/9100KG
A127: =ROW( ) -3 -> 124 | B127: =VLOOKUP(D127,DSKH!$A:$B,2,0) -> A-590 | C127: HOÀNG | D127: YUEDA | E127: N | F127: 108113852930 | G127: E15 | H127: 46114 | I127: NL | J127: X | K127: TN | M127: 19 | S127: 1 | T127: 1380K/8971KG
A128: =ROW( ) -3 -> 125 | B128: =VLOOKUP(D128,DSKH!$A:$B,2,0) -> A-590 | C128: HOÀNG | D128: YUEDA | E128: N | F128: 108113994330 | G128: E15 | H128: 46114 | I128: NL | J128: X | K128: TN | M128: 1177 | S128: 1 | T128: 1050K/10396KG
A129: =ROW( ) -3 -> 126 | B129: =VLOOKUP(D129,DSKH!$A:$B,2,0) -> A-590 | C129: HOÀNG | D129: YUEDA | E129: N | F129: 108114078440 | G129: E13 | H129: 46114 | I129: NL | J129: X | K129: TN | M129: 56 | S129: 1 | T129: 6K/560KG
A130: =ROW( ) -3 -> 127 | B130: =VLOOKUP(D130,DSKH!$A:$B,2,0) -> A-590 | C130: HOÀNG | D130: YUEDA | E130: N | F130: 108028226350 | H130: 46087 | K130: TN | Y130: TỜ KHAI THÁNG 3, THU BỔ SUNG GIẤY PHÉP NHẬP KHẨU
A131: =ROW( ) -3 -> 128 | B131: =VLOOKUP(D131,DSKH!$A:$B,2,0) -> A-518 | C131: HOÀI | D131: SPORTPET | E131: N | F131: 108106046530 | G131: A12 | H131: 46113 | I131: NL | J131: V | K131: TN | L131: E | M131: IL26-0009 | N131: 130326721346641 | Q131: 1 | T131: 497K/26105KG | U131: UETU8028011 | V131: 202611312713 | W131: 500000 | X131: CAT LAI
A132: =ROW( ) -3 -> 129 | B132: =VLOOKUP(D132,DSKH!$A:$B,2,0) -> A-131 | C132: HOÀI | D132: OPTIMA/LYNN | E132: X | F132: 308387395800 | G132: B11 | H132: 46113 | I132: NL | J132: X | K132: DN3 | M132: 8650206454 | R132: 1 | T132: 8K/53KG | X132: ITL BINH DUONG
A133: =ROW( ) -3 -> 130 | B133: =VLOOKUP(D133,DSKH!$A:$B,2,0) -> A-131 | C133: HOÀI | D133: OPTIMA/LYNN | E133: X | F133: 308387468340 | G133: B11 | H133: 46113 | I133: NL | J133: X | K133: DN3 | M133: 8650203758 | R133: 1 | T133: 758K/3604KG | X133: TBS
...

Sheet THÁNG 5_Tổng hợp
A1: STT | B1: MÃ KHÁCH HÀNG | C1: NHÂN VIÊN | D1: KHÁCH HÀNG | E1: CÔNG VIỆC | F1: SỐ TỜ KHAI | G1: LOẠI HÌNH | H1: NGÀY TỜ KHAI | I1: LOẠI HÀNG | J1: LUỒNG TK | K1: HẢI QUAN | L1: C/O | M1: SỐ INV/VAT | N1: SỐ BILL | O1: SỐ BOOKING | P1: SỐ LƯỢNG | T1: (KIỆN, KG) | U1: SỐ CONTAINER | V1: THÔNG BÁO PHÍ CSHT | W1: SỐ TIỀN CSHT | X1: CẢNG XUẤT - CẢNG NHẬP | Y1: GHI CHÚ | Z1: TRẠNG THÁI LÔ HÀNG
P2: 20' | Q2: 40' | R2: LCL | S2: TC
A4: 1 | B4: =VLOOKUP(D4,DSKH!$A:$B,2,0) -> A-17 | C4: KHÁCH | D4: NHỰA RELIABLE | E4: N | F4: 108203836640 | G4: A12 | H4: 46146 | I4: NL | J4: V | K4: BH | L4: E | M4: INVJYSP260316ZKXS-2515 | N4: 268974350 | Q4: 5 | U4: CAAU8933871 TGBU5255289 SUDU5917584 CAAU4697490 CAAU6445435 | V4: V3PHT202611562425 | W4: 2500000 | X4: CÁT LÁI
A5: 2 | B5: =VLOOKUP(D5,DSKH!$A:$B,2,0) -> A-39 | C5: KHÁCH | D5: TIGER | E5: N | F5: 108201269850 | G5: E31 | H5: 46146 | I5: NL | J5: X | K5: BH | M5: 260401-MFP | N5: HKHCM26045016 | R5: 1 | T5: 3K / 34,9KG | X5: CÁT LÁI
A6: 3 | B6: =VLOOKUP(D6,DSKH!$A:$B,2,0) -> A-39 | C6: KHÁCH | D6: TIGER | E6: N | F6: 108201342650 | G6: E31 | H6: 46146 | I6: NL | J6: X | K6: BH | M6: 0497849 | N6: CMSSH26041680 | R6: 1 | T6: 1K / 378KG | X6: CÁT LÁI
A7: 4 | B7: =VLOOKUP(D7,DSKH!$A:$B,2,0) -> A-39 | C7: KHÁCH | D7: TIGER | E7: N | F7: 108201487700 | G7: E31 | H7: 46146 | I7: NL | J7: X | K7: BH | M7: 60812 | N7: FCO0035227 | R7: 1 | T7: 10K / 110,6KG | X7: SCSC
A8: 5 | B8: =VLOOKUP(D8,DSKH!$A:$B,2,0) -> A-39 | C8: KHÁCH | D8: TIGER | E8: N | F8: 108201888540 | G8: E31 | H8: 46146 | I8: NL | J8: V | K8: BH | M8: 12JE-26-EN99-VG11 | N8: OOLU2323380380 | Q8: 1 | U8: TIIU5180738 | V8: V3PHT202611558851 | W8: 500000 | X8: SP ITC
A9: 6 | B9: =VLOOKUP(D9,DSKH!$A:$B,2,0) -> A-39 | C9: KHÁCH | D9: TIGER | E9: N | F9: 108214433020 | G9: E31 | H9: 46148 | I9: NL | J9: X | K9: BH | M9: STE-VT26006 | N9: TL260426HCM75 | R9: 1 | T9: 1K / 298,45KG | X9: CÁT LÁI
A10: 7 | B10: =VLOOKUP(D10,DSKH!$A:$B,2,0) -> A-27 | C10: KHÁCH | D10: TRUNG ĐÔNG | E10: N | F10: 108201879920 | G10: E31 | H10: 46146 | I10: NL | J10: X | K10: DN3 | M10: IT-SI-12597 | N10: HLCUTA12603FZNZ3 | Q10: 7 | U10: BMOU5622781 FCIU7447520 GCXU5947094 HAMU4070700 HLBU2267900 SEKU6359096 UETU7560694 | X10: CÁT LÁI
A11: 8 | B11: =VLOOKUP(D11,DSKH!$A:$B,2,0) -> A-27 | C11: KHÁCH | D11: TRUNG ĐÔNG | E11: N | F11: 108204380800 | G11: A12 | H11: 46146 | I11: NL | J11: V | K11: DN3 | M11: 40205167 | N11: PCLUINC01545155 | Q11: 8 | U11: DFSU7647477 FSCU8501040 PCLU5112775 PCLU5163026 PCLU5223819 TEMU8886760 TGBU5574096 TIIU6649199 | X11: CÁT LÁI
A12: 9 | B12: =VLOOKUP(D12,DSKH!$A:$B,2,0) -> A-17 | C12: KHÁCH | D12: NHỰA RELIABLE | E12: N | F12: 108216737200 | G12: A12 | H12: 46149 | I12: NL | J12: V | K12: BH | L12: E | M12: INVJYSP260330ZKXS-2587 | N12: YMJAI221205448 | Q12: 10 | U12: BMOU6144917 BMOU6204220 FFAU6998136 TIIU4666900 SEGU6511687 YMMU6623561 YMMU7182389 TGBU5091420 YMLU8668577 YMMU6291981 | V12: V3PHT202611595618 | W12: 5000000 | X12: CÁT LÁI
A13: 10 | B13: =VLOOKUP(D13,DSKH!$A:$B,2,0) -> A-17 | C13: KHÁCH | D13: NHỰA RELIABLE | E13: N | F13: 108216768700 | G13: A12 | H13: 46149 | I13: NL | J13: V | K13: BH | L13: D | M13: INVE-26-00016 | N13: NAY04260484HCM | P13: 1 | U13: SEGU1296658 | V13: V3PHT264078434618 | W13: 250000 | X13: CÁT LÁI
A14: 11 | B14: =VLOOKUP(D14,DSKH!$A:$B,2,0) -> A-213 | C14: THẢO | D14: REGENT | E14: N | F14: 108203315620 | G14: A12 | H14: 46146 | I14: NL | J14: V | K14: NT | L14: E | M14: 20260424001 | N14: LLLHCM26423226 | R14: 1 | T14: 5K/4,792KG | V14: 263572082440 | W14: 71880 | X14: CAT LAI
A15: 12 | B15: =VLOOKUP(D15,DSKH!$A:$B,2,0) -> A-213 | C15: THẢO | D15: REGENT | E15: X | F15: 308492314560 | G15: B11 | H15: 46146 | I15: NL | J15: X | K15: NT | M15: 20 | S15: 1 | T15: 6K/22,15KG
A16: 13 | B16: =VLOOKUP(D16,DSKH!$A:$B,2,0) -> A-213 | C16: THẢO | D16: REGENT | E16: X | F16: 308495483720 | G16: B11 | H16: 46147 | I16: NL | J16: X | K16: NT | M16: 20260504001 | S16: 1 | T16: 154K/5,290,6KG | Y16: TK CHUNG LO
A17: 14 | B17: =VLOOKUP(D17,DSKH!$A:$B,2,0) -> A-213 | C17: THẢO | D17: REGENT | E17: X | F17: 308495505750 | G17: B11 | H17: 46147 | I17: NL | J17: X | K17: NT
A18: 15 | B18: =VLOOKUP(D18,DSKH!$A:$B,2,0) -> A-213 | C18: THẢO | D18: REGENT | E18: X | F18: 308495517100 | G18: B11 | H18: 46147 | I18: NL | J18: X | K18: NT
A19: 16 | B19: =VLOOKUP(D19,DSKH!$A:$B,2,0) -> A-213 | C19: THẢO | D19: REGENT | E19: X | F19: 308495538760 | G19: B11 | H19: 46147 | I19: NL | J19: X | K19: NT
A20: 17 | B20: =VLOOKUP(D20,DSKH!$A:$B,2,0) -> A-224 | C20: THẢO | D20: PU ZHOU | E20: N | F20: 108206082940 | G20: A12 | H20: 46146 | I20: NL | J20: V | K20: NT | L20: E | M20: PZP260402 | N20: LDGHCM2641641SZ | R20: 1 | T20: 4K/3,971KG | V20: 266065321301 | W20: 59565 | X20: CAT LAI
A21: 18 | B21: =VLOOKUP(D21,DSKH!$A:$B,2,0) -> A-556 | C21: THẢO | D21: V.L.I | E21: X | F21: 308493468310 | G21: E52 | H21: 46146 | I21: NL | J21: X | K21: TN | M21: 56-0526-06 VLI-MSY | S21: 1 | T21: 289K/2.257,37KG
A22: 19 | B22: =VLOOKUP(D22,DSKH!$A:$B,2,0) -> A-564 | C22: THẢO | D22: PHOENIX | E22: X | F22: 308492936310 | G22: B11 | H22: 46146 | I22: NL | J22: X | K22: TN | M22: 38 | S22: 1 | T22: 15K/10.283KG
A23: 20 | B23: =VLOOKUP(D23,DSKH!$A:$B,2,0) -> A-502 | C23: THẢO | D23: RYDER | E23: N | F23: 108203697560 | G23: E31 | H23: 46146 | I23: NL | J23: V | K23: DN3 | M23: 2252026 | N23: 4288709165 | R23: 1 | T23: 1K/6,1KG | X23: DHL
A24: 21 | B24: =VLOOKUP(D24,DSKH!$A:$B,2,0) -> A-502 | C24: THẢO | D24: RYDER | E24: N | F24: 108202761660 | G24: A12 | H24: 46146 | I24: MMTB | J24: V | K24: DN3 | M24: VN260428XF-FEDEX-N | N24: 412669261295 | R24: 1 | T24: 2K/3,5KG | X24: FEDEX
A25: 22 | B25: =VLOOKUP(D25,DSKH!$A:$B,2,0) -> A-502 | C25: THẢO | D25: RYDER | E25: N | F25: 108205058840 | G25: E31 | H25: 46146 | I25: NL | J25: X | K25: DN3 | M25: M20260429RIL-FEDEX-HK-B | N25: 412669357398 | R25: 1 | T25: 2K/4,5KG | X25: FEDEX
A26: 23 | B26: =VLOOKUP(D26,DSKH!$A:$B,2,0) -> A-502 | C26: THẢO | D26: RYDER | E26: N | F26: 108205201530 | G26: E31 | H26: 46146 | I26: NL | J26: X | K26: DN3 | M26: M20260429XF-FEDEX-SZ | N26: 412669261332 | R26: 1 | T26: 4K/32,7KG | X26: FEDEX
A27: 24 | B27: =VLOOKUP(D27,DSKH!$A:$B,2,0) -> A-502 | C27: THẢO | D27: RYDER | E27: X | F27: 308491418820 | G27: E62 | H27: 46147 | I27: NL | J27: X | K27: DN3 | M27: RD260506-BOA-VN | R27: 1 | T27: 4K/1.003,1KG | X27: KNQ LF LOGISTICS | Y27: TK CHUNG LO
A28: 25 | B28: =VLOOKUP(D28,DSKH!$A:$B,2,0) -> A-502 | C28: THẢO | D28: RYDER | E28: X | F28: 308491425340 | G28: E62 | H28: 46147 | I28: NL | J28: X | K28: DN3
A29: 26 | B29: =VLOOKUP(D29,DSKH!$A:$B,2,0) -> A-213 | C29: THẢO | D29: REGENT | E29: N | F29: 108210590720 | G29: A12 | H29: 46147 | I29: NL | J29: V | K29: NT | L29: E | M29: 20260418001 | N29: MEDUYO572919 | Q29: 1 | T29: 63K/20.025,1KG | U29: FFAU2975791 | V29: 202611578240 | W29: 500000 | X29: SP-ITC | Y29: TK CHUNG LO 56/SKHCN-TDC
A30: 27 | B30: =VLOOKUP(D30,DSKH!$A:$B,2,0) -> A-213 | C30: THẢO | D30: REGENT | E30: N | F30: 108210609840 | G30: A12 | H30: 46147 | I30: THEP | J30: V | K30: NT | L30: E
A31: 28 | B31: =VLOOKUP(D31,DSKH!$A:$B,2,0) -> A-213 | C31: THẢO | D31: REGENT | E31: X | F31: 308497389450 | G31: B11 | H31: 46147 | I31: NL | J31: X | K31: NT | M31: 20260504002 | S31: 1 | T31: 101K/203,02KG | Y31: TK CHUNG LO
A32: 29 | B32: =VLOOKUP(D32,DSKH!$A:$B,2,0) -> A-213 | C32: THẢO | D32: REGENT | E32: X | F32: 308497401350 | G32: B11 | H32: 46147 | I32: NL | J32: X | K32: NT
A33: 30 | B33: =VLOOKUP(D33,DSKH!$A:$B,2,0) -> A-213 | C33: THẢO | D33: REGENT | E33: X | F33: 308497413360 | G33: B11 | H33: 46147 | I33: NL | J33: X | K33: NT
A34: 31 | B34: =VLOOKUP(D34,DSKH!$A:$B,2,0) -> A-213 | C34: THẢO | D34: REGENT | E34: X | F34: 308498534430 | G34: B11 | H34: 46147 | I34: NL | J34: X | K34: NT | M34: 20260504003 | S34: 1 | T34: 186K/1.425,86KG | Y34: TK CHUNG LO
A35: 32 | B35: =VLOOKUP(D35,DSKH!$A:$B,2,0) -> A-213 | C35: THẢO | D35: REGENT | E35: X | F35: 308498542350 | G35: B11 | H35: 46147 | I35: NL | J35: X | K35: NT
A36: 33 | B36: =VLOOKUP(D36,DSKH!$A:$B,2,0) -> A-213 | C36: THẢO | D36: REGENT | E36: X | F36: 308498548430 | G36: B11 | H36: 46147 | I36: NL | J36: X | K36: NT
A37: 34 | B37: =VLOOKUP(D37,DSKH!$A:$B,2,0) -> A-213 | C37: THẢO | D37: REGENT | E37: X | F37: 308498557420 | G37: B11 | H37: 46147 | I37: NL | J37: X | K37: NT
A38: 35 | B38: =VLOOKUP(D38,DSKH!$A:$B,2,0) -> A-213 | C38: THẢO | D38: REGENT | E38: X | F38: 308498620750 | G38: B11 | H38: 46147 | I38: NL | J38: X | K38: NT | M38: 20260505001 | S38: 1 | T38: 9K/75,51KG
A39: 36 | B39: =VLOOKUP(D39,DSKH!$A:$B,2,0) -> A-323 | C39: THẢO | D39: AICA | E39: N | F39: 108207400710 | G39: A12 | H39: 46147 | I39: NL | J39: V | K39: NT | L39: E | M39: 421/ICA-INV/III/26 | N39: SAA260306602 | P39: 4 | T39: 160K/80.880KG | U39: SKLU1668296 SKLU1922780 SKLU1937570 SKLU2076049 | X39: CAT LAI | Y39: 8MQ-0041777
A40: 37 | B40: =VLOOKUP(D40,DSKH!$A:$B,2,0) -> A-323 | C40: THẢO | D40: AICA | E40: N | F40: 108207767510 | G40: A12 | H40: 46147 | I40: NL | J40: V | K40: NT | L40: RCEP | M40: ALV-26-018 | N40: TYJPVN260846 | Q40: 1 | T40: 48K/5.232KG | U40: TWCU8104180 | X40: CAT LAI
A41: 38 | B41: =VLOOKUP(D41,DSKH!$A:$B,2,0) -> A-213 | C41: THẢO | D41: REGENT | E41: X | F41: 308500491410 | G41: B11 | H41: 46148 | I41: NL | J41: X | K41: NT | M41: 20260505002 | S41: 1 | T41: 195K/14.484,55KG | Y41: TK CHUNG LO
A42: 39 | B42: =VLOOKUP(D42,DSKH!$A:$B,2,0) -> A-213 | C42: THẢO | D42: REGENT | E42: X | F42: 308500508100 | G42: B11 | H42: 46148 | I42: NL | J42: X | K42: NT
A43: 40 | B43: =VLOOKUP(D43,DSKH!$A:$B,2,0) -> A-213 | C43: THẢO | D43: REGENT | E43: X | F43: 308500515540 | G43: B11 | H43: 46148 | I43: NL | J43: X | K43: NT
A44: 41 | B44: =VLOOKUP(D44,DSKH!$A:$B,2,0) -> A-213 | C44: THẢO | D44: REGENT | E44: X | F44: 308500527700 | G44: B11 | H44: 46148 | I44: NL | J44: X | K44: NT
A45: 42 | B45: =VLOOKUP(D45,DSKH!$A:$B,2,0) -> A-213 | C45: THẢO | D45: REGENT | E45: X | F45: 308500669650 | G45: B11 | H45: 46148 | I45: NL | J45: X | K45: NT | M45: 20260505003 | S45: 1 | T45: 35K/289,9KG
A46: 43 | B46: =VLOOKUP(D46,DSKH!$A:$B,2,0) -> A-224 | C46: THẢO | D46: PU ZHOU | E46: N | F46: 108212080320 | G46: A12 | H46: 46148 | I46: NL | J46: V | K46: NT | M46: PZ260410 | N46: NZLTAO26003497 | P46: 1 | T46: 25K/25.375KG | U46: ECMU1565396 | V46: 202611583262 | W46: 250000 | X46: CAT LAI
A47: 44 | B47: =VLOOKUP(D47,DSKH!$A:$B,2,0) -> A-323 | C47: THẢO | D47: AICA | E47: X | F47: 308500864950 | G47: B11 | H47: 46148 | I47: NL | J47: X | K47: NT | M47: ALV-WSH-26005 | O47: 235600715422 | Q47: 2 | T47: 12K/22.000KG | U47: EMCU5404450 EMCU5439333 | X47: CAT LAI | Y47: KHÔNG VẬN CHUYỂN
A48: 45 | B48: =VLOOKUP(D48,DSKH!$A:$B,2,0) -> A-556 | C48: THẢO | D48: V.L.I | E48: N | F48: 108214135520 | G48: E21 | H48: 46148 | I48: NL | J48: X | K48: TN | M48: VLI-HD56-26006 | S48: 1 | T48: 1.206K/10.537,9KG
A49: 46 | B49: =VLOOKUP(D49,DSKH!$A:$B,2,0) -> A-502 | C49: THẢO | D49: RYDER | E49: N | F49: 108206955140 | G49: G51 | H49: 46148 | I49: NL | J49: V | K49: DN3 | M49: VN260424-SZ-TN | N49: 871030487169 | R49: 1 | T49: 1K/5,5KG | X49: FEDEX
A50: 47 | B50: =VLOOKUP(D50,DSKH!$A:$B,2,0) -> A-323 | C50: THẢO | D50: AICA | E50: N | F50: 108213428040 | G50: A12 | H50: 46149 | I50: NL | J50: V | K50: NT | L50: D | M50: CI-26040136-CR | N50: NSSLIKHCC2600309 | P50: 1 | Q50: 1 | T50: 30K/18.768KG | U50: DYLU5157730 SEKU1370174 | X50: CAT LAI
A51: 48 | B51: =VLOOKUP(D51,DSKH!$A:$B,2,0) -> A-323 | C51: THẢO | D51: AICA | E51: N | F51: 108216196060 | G51: A12 | H51: 46149 | I51: NL | J51: V | K51: NT | L51: JV | M51: ALV-26-020 | N51: 546040095001 | Q51: 4 | T51: 281K/54.364KG | U51: CSNU6913938 OOLU9855920 TCNU4452529 TCNU6244458 | X51: SP-ITC | Y51: TK CHUNG LO FMK-0043182
A52: 49 | B52: =VLOOKUP(D52,DSKH!$A:$B,2,0) -> A-323 | C52: THẢO | D52: AICA | E52: N | F52: 108216263410 | G52: A12 | H52: 46149 | I52: NL | J52: V | K52: NT | L52: JV
A53: 50 | B53: =VLOOKUP(D53,DSKH!$A:$B,2,0) -> A-323 | C53: THẢO | D53: AICA | E53: X | F53: 308504295100 | G53: B11 | H53: 46149 | I53: NL | J53: X | K53: NT | M53: ALV-WSH-26006 | O53: 235600715422 | Q53: 3 | T53: 20K/37.000KG | U53: EMCU5450693 EMCU5428508 EMCU5407486 | X53: CAT LAI | Y53: KHÔNG VẬN CHUYỂN
A54: 51 | B54: =VLOOKUP(D54,DSKH!$A:$B,2,0) -> A-323 | C54: THẢO | D54: AICA | E54: X | F54: 308504460740 | G54: B11 | H54: 46149 | I54: NL | J54: X | K54: NT | M54: ALV-AKCJ-26-032 | O54: 2326671390 | Q54: 2 | T54: 64K/43.000KG | U54: TGBU8827048 SEKU4642656 | X54: CAT LAI | Y54: KHÔNG VẬN CHUYỂN
A55: 52 | B55: =VLOOKUP(D55,DSKH!$A:$B,2,0) -> A-323 | C55: THẢO | D55: AICA | E55: X | F55: 308505020040 | G55: B11 | H55: 46149 | I55: NL | J55: X | K55: NT | M55: ALV-WSATH-26025 | O55: SG2606175 | P55: 1 | T55: 3K/3.000KG | U55: SEKU1603851 | X55: CAT LAI | Y55: TK CHUNG LO
A56: 53 | B56: =VLOOKUP(D56,DSKH!$A:$B,2,0) -> A-323 | C56: THẢO | D56: AICA | E56: X | F56: 308505040010 | G56: B11 | H56: 46149 | I56: NL | J56: X | K56: NT | M56: ALV-WSATH-26026 | T56: 6K/6.500KG
A57: 54 | B57: =VLOOKUP(D57,DSKH!$A:$B,2,0) -> A-564 | C57: THẢO | D57: PHOENIX | E57: X | F57: 308504510810 | G57: B11 | H57: 46149 | I57: NL | J57: V | K57: TN | M57: 39 | S57: 1 | T57: 10K/8.099KG
A58: 55 | B58: =VLOOKUP(D58,DSKH!$A:$B,2,0) -> A-502 | C58: THẢO | D58: RYDER | E58: N | F58: 108219188820 | G58: E21 | H58: 46149 | I58: NL | J58: X | K58: DN3 | M58: TR03964/TR03993 | R58: 1 | T58: 81K/619,06KG | X58: KNQ LF LOGISTICS
A59: 56 | B59: =VLOOKUP(D59,DSKH!$A:$B,2,0) -> A-502 | C59: THẢO | D59: RYDER | E59: X | F59: 308502342210 | G59: E52 | H59: 46149 | I59: NL | J59: X | K59: DN3 | M59: RD260508GC32-BOA-VNGC | R59: 1 | T59: 2K/803,69KG | X59: KNQ LF LOGISTICS
A60: 57 | B60: =VLOOKUP(D60,DSKH!$A:$B,2,0) -> A-502 | C60: THẢO | D60: RYDER | E60: X | F60: 308503260500 | G60: E62 | H60: 46149 | I60: NL | J60: X | K60: DN3 | M60: RD260508-BOA-VN | R60: 1 | T60: 17K/5.354,7KG | X60: KNQ LF LOGISTICS | Y60: TK CHUNG LO
A61: 58 | B61: =VLOOKUP(D61,DSKH!$A:$B,2,0) -> A-502 | C61: THẢO | D61: RYDER | E61: X | F61: 308503265030 | G61: E62 | H61: 46149 | I61: NL | J61: X | K61: DN3
A62: 59 | B62: =VLOOKUP(D62,DSKH!$A:$B,2,0) -> A-502 | C62: THẢO | D62: RYDER | E62: X | F62: 308503267460 | G62: E62 | H62: 46149 | I62: NL | J62: X | K62: DN3
A63: 60 | B63: =VLOOKUP(D63,DSKH!$A:$B,2,0) -> A-502 | C63: THẢO | D63: RYDER | E63: X | F63: 308503271440 | G63: E62 | H63: 46149 | I63: NL | J63: X | K63: DN3
A64: 61 | B64: =VLOOKUP(D64,DSKH!$A:$B,2,0) -> A-502 | C64: THẢO | D64: RYDER | E64: X | F64: 308503274500 | G64: E62 | H64: 46149 | I64: NL | J64: X | K64: DN3
A65: 62 | B65: =VLOOKUP(D65,DSKH!$A:$B,2,0) -> A-502 | C65: THẢO | D65: RYDER | E65: N | F65: 108211171830 | G65: A12 | H65: 46150 | I65: MMTB | J65: X | K65: DN3 | M65: APD20260413001 | N65: HWD2604095 | R65: 1 | T65: 2K/1.472KG | V65: 202611606054 | W65: 22080 | X65: CAT LAI
A66: 63 | B66: =VLOOKUP(D66,DSKH!$A:$B,2,0) -> A-502 | C66: THẢO | D66: RYDER | E66: N | F66: 108221176560 | G66: E31 | H66: 46150 | I66: NL | J66: X | K66: DN3 | M66: M20260507XF-DHL-HK | N66: 1025296823 | R66: 1 | T66: 1K/0,7KG | X66: DHL
A67: 64 | B67: =VLOOKUP(D67,DSKH!$A:$B,2,0) -> A-224 | C67: THẢO | D67: PU ZHOU | E67: N | F67: 108219980520 | G67: A12 | H67: 46150 | I67: NL | J67: V | K67: NT | L67: E | M67: PZ260417 | N67: JJCQDSGA6430124 | P67: 1 | T67: 25K/25.375KG | U67: TWCU2227130 | V67: 202611603816 | W67: 250000 | X67: CAT LAI
A68: 65 | B68: =VLOOKUP(D68,DSKH!$A:$B,2,0) -> A-323 | C68: THẢO | D68: AICA | E68: N | F68: 108219767500 | G68: A12 | H68: 46150 | I68: NL | J68: V | K68: NT | L68: JV | M68: ALV-26-021 | N68: 546040128001 | Q68: 4 | T68: 263K/64.549KG | U68: OOLU9995428 OOCU9198480 CCLU7727354 OOCU9080250 | X68: SP-ITC
A69: 66 | B69: =VLOOKUP(D69,DSKH!$A:$B,2,0) -> A-213 | C69: THẢO | D69: REGENT | E69: X | F69: 308507622160 | G69: B11 | H69: 46150 | I69: NL | J69: X | K69: NT | M69: 20260507001 | S69: 1 | T69: 127K/2.935,29KG | Y69: TK CHUNG LO
A70: 67 | B70: =VLOOKUP(D70,DSKH!$A:$B,2,0) -> A-213 | C70: THẢO | D70: REGENT | E70: X | F70: 308507631630 | G70: B11 | H70: 46150 | I70: NL | J70: X | K70: NT
A71: 68 | B71: =VLOOKUP(D71,DSKH!$A:$B,2,0) -> A-213 | C71: THẢO | D71: REGENT | E71: X | F71: 308507645520 | G71: B11 | H71: 46150 | I71: NL | J71: X | K71: NT
A72: 69 | B72: =VLOOKUP(D72,DSKH!$A:$B,2,0) -> A-213 | C72: THẢO | D72: REGENT | E72: X | F72: 308508819050 | G72: B11 | H72: 46150 | I72: NL | J72: X | K72: NT | M72: 20260508001 | S72: 1 | T72: 51K/166,06KG | Y72: TK CHUNG LO
A73: 70 | B73: =VLOOKUP(D73,DSKH!$A:$B,2,0) -> A-213 | C73: THẢO | D73: REGENT | E73: X | F73: 308508831650 | G73: B11 | H73: 46150 | I73: NL | J73: X | K73: NT
A74: 71 | B74: =VLOOKUP(D74,DSKH!$A:$B,2,0) -> A-213 | C74: THẢO | D74: REGENT | E74: X | F74: 308510175060 | G74: B11 | H74: 46150 | I74: NL | J74: X | K74: NT | M74: 20260507002 | S74: 1 | T74: 159K/529,41KG | Y74: TK CHUNG LO
A75: 72 | B75: =VLOOKUP(D75,DSKH!$A:$B,2,0) -> A-213 | C75: THẢO | D75: REGENT | E75: X | F75: 308510193850 | G75: B11 | H75: 46150 | I75: NL | J75: X | K75: NT
A76: 73 | B76: =VLOOKUP(D76,DSKH!$A:$B,2,0) -> A-213 | C76: THẢO | D76: REGENT | E76: X | F76: 308510208660 | G76: B11 | H76: 46150 | I76: NL | J76: X | K76: NT
A77: 74 | B77: =VLOOKUP(D77,DSKH!$A:$B,2,0) -> A-213 | C77: THẢO | D77: REGENT | E77: X | F77: 308510221740 | G77: B11 | H77: 46150 | I77: NL | J77: X | K77: NT
A78: 75 | B78: =VLOOKUP(D78,DSKH!$A:$B,2,0) -> A-323 | C78: THẢO | D78: AICA | E78: X | F78: 308508553640 | G78: B11 | H78: 46150 | I78: NL | J78: X | K78: NT | M78: ALV-AKCJ-26-033 | O78: 2326671390 | Q78: 4 | T78: 83K/70.000KG | U78: OOLU9855920 OOCU7019164 TCNU4452529 TCNU6244458 | X78: CAT LAI
A79: 76 | B79: =VLOOKUP(D79,DSKH!$A:$B,2,0) -> A-212 | C79: GIA HUY | D79: LEADER | E79: N | F79: 108224304900 | G79: E15 | H79: 46151 | I79: NL | J79: XANH | K79: TN | S79: 1
A80: 77 | B80: =VLOOKUP(D80,DSKH!$A:$B,2,0) -> A-212 | C80: GIA HUY | D80: LEADER | E80: N | F80: 108224375710 | G80: E15 | H80: 46151 | I80: NL | J80: XANH | K80: TN | S80: 1
A81: 78 | B81: =VLOOKUP(D81,DSKH!$A:$B,2,0) -> A-12 | C81: MINH | D81: MATSUYA | E81: X | F81: 308493552750 | G81: E42 | H81: 46146 | I81: NL | J81: XANH | K81: TN | M81: 256 | S81: 1 | T81: 30K/9.572,04KG
A82: 79 | B82: =VLOOKUP(D82,DSKH!$A:$B,2,0) -> A-12 | C82: MINH | D82: MATSUYA | E82: X | F82: 308497584530 | G82: E42 | H82: 46147 | I82: NL | J82: XANH | K82: TN | M82: 260 | S82: 1 | T82: 28K/8.705,81KG
A83: 80 | B83: =VLOOKUP(D83,DSKH!$A:$B,2,0) -> A-12 | C83: MINH | D83: MATSUYA | E83: X | F83: 308498531300 | G83: E42 | H83: 46147 | I83: NL | J83: XANH | K83: TN | M83: 261 | S83: 1 | T83: 3K/773,66KG
A84: 81 | B84: =VLOOKUP(D84,DSKH!$A:$B,2,0) -> A-12 | C84: MINH | D84: MATSUYA | E84: X | F84: 308501178920 | G84: E42 | H84: 46148 | I84: NL | J84: XANH | K84: TN | M84: 264 | S84: 1 | T84: 32K/11.044,48KG
A85: 82 | B85: =VLOOKUP(D85,DSKH!$A:$B,2,0) -> A-12 | C85: MINH | D85: MATSUYA | E85: X | F85: 308501563810 | G85: E42 | H85: 46148 | I85: NL | J85: XANH | K85: TN | M85: 265 | S85: 1 | T85: 3K/200KG
A86: 83 | B86: =VLOOKUP(D86,DSKH!$A:$B,2,0) -> A-12 | C86: MINH | D86: MATSUYA | E86: X | F86: 308504804920 | G86: E42 | H86: 46149 | I86: NL | J86: XANH | K86: TN | M86: 270 | S86: 1 | T86: 35K/10.876,53KG
A87: 84 | B87: =VLOOKUP(D87,DSKH!$A:$B,2,0) -> A-12 | C87: MINH | D87: MATSUYA | E87: X | F87: 308510234930 | G87: E42 | H87: 46150 | I87: NL | J87: XANH | K87: TN | M87: 274 | S87: 1 | T87: 9K/2.120,15KG
A88: 85 | B88: =VLOOKUP(D88,DSKH!$A:$B,2,0) -> A-12 | C88: MINH | D88: MATSUYA | E88: X | F88: 308510245060 | G88: E42 | H88: 46150 | I88: NL | J88: XANH | K88: TN | M88: 276 | S88: 1 | T88: 30K/9.761,94KG
A89: 86 | B89: =VLOOKUP(D89,DSKH!$A:$B,2,0) -> B-57 | C89: HÀ | D89: HONGSEN - TQQT | E89: X | F89: 308493705350 | G89: B11 | H89: 46146 | I89: NL | J89: X | K89: TN | M89: 198 | S89: 1 | T89: 480PK/2960,49KG
A90: 87 | B90: =VLOOKUP(D90,DSKH!$A:$B,2,0) -> B-57 | C90: HÀ | D90: HONGSEN - TQQT | E90: X | F90: 308494940630 | G90: B11 | H90: 46146 | I90: NL | J90: X | K90: TN | M90: 199 | S90: 1 | T90: 612PK/3800,52KG
A91: 88 | B91: =VLOOKUP(D91,DSKH!$A:$B,2,0) -> B-57 | C91: HÀ | D91: HONGSEN - TQQT | E91: X | F91: 308494941550 | G91: B11 | H91: 46146 | I91: NL | J91: X | K91: TN | M91: 200 | S91: 1 | T91: 714PK/3949,64KG
A92: 89 | B92: =VLOOKUP(D92,DSKH!$A:$B,2,0) -> B-57 | C92: HÀ | D92: HONGSEN - TQQT | E92: X | F92: 308494942140 | G92: B11 | H92: 46146 | I92: NL | J92: X | K92: TN | M92: 201 | S92: 1 | T92: 806PK/6099,19KG
A93: 90 | B93: =VLOOKUP(D93,DSKH!$A:$B,2,0) -> B-57 | C93: HÀ | D93: HONGSEN - TQQT | E93: X | F93: 308494943100 | G93: B11 | H93: 46146 | I93: NL | J93: X | K93: TN | M93: 202 | S93: 1 | T93: 876PK/6357,15KG
A94: 91 | B94: =VLOOKUP(D94,DSKH!$A:$B,2,0) -> #N/A | C94: HÀ | D94: GIPT - TQVD | E94: X | F94: 308491649820 | G94: E62 | H94: 46146 | I94: NL | J94: X | K94: TN | M94: TIT260501 | R94: 1 | T94: 11PP/3571,19KG | X94: KNQ
A95: 92 | B95: =VLOOKUP(D95,DSKH!$A:$B,2,0) -> #N/A | C95: HÀ | D95: GIPT - TQVD | E95: X | F95: 308491982910 | G95: E62 | H95: 46146 | I95: NL | J95: X | K95: TN | M95: WLV260501 | R95: 1 | T95: 7PP/3406,52KG | X95: KNQ
A96: 93 | B96: =VLOOKUP(D96,DSKH!$A:$B,2,0) -> #N/A | C96: HÀ | D96: GIPT - TQVD | E96: X | F96: 308491999710 | G96: E62 | H96: 46146 | I96: NL | J96: X | K96: TN | M96: PNX260501 | R96: 1 | T96: 7PP/2894,33KG | X96: KNQ
A97: 94 | B97: =VLOOKUP(D97,DSKH!$A:$B,2,0) -> #N/A | C97: HÀ | D97: GIPT - TQVD | E97: X | F97: 308492959260 | G97: E62 | H97: 46146 | I97: NL | J97: X | K97: TN | M97: FRW260501 | R97: 1 | T97: 40PP/12883,18KG | X97: KNQ | Y97: CHUNG LÔ
A98: 95 | B98: =VLOOKUP(D98,DSKH!$A:$B,2,0) -> #N/A | C98: HÀ | D98: GIPT - TQVD | E98: X | F98: 308492984610 | G98: E62 | H98: 46146 | I98: NL | J98: X | K98: TN
A99: 96 | B99: =VLOOKUP(D99,DSKH!$A:$B,2,0) -> #N/A | C99: HÀ | D99: GIPT - TQVD | E99: N | F99: 108205553850 | G99: E31 | H99: 46146 | I99: NL | J99: X | K99: TN | M99: WUGIP260422-01 | N99: 870938014827 | R99: 1 | T99: 5PK/20KG | X99: FEDEX
A100: 97 | B100: =VLOOKUP(D100,DSKH!$A:$B,2,0) -> #N/A | C100: HÀ | D100: GIPT - TQVD | E100: N | F100: 108205687110 | G100: E31 | H100: 46146 | I100: NL | J100: X | K100: TN | M100: MI260428002 | N100: 871145242689 | R100: 1 | T100: 2PK/8,8KG | X100: FEDEX
A101: 98 | B101: =VLOOKUP(D101,DSKH!$A:$B,2,0) -> #N/A | C101: HÀ | D101: GIPT - TQVD | E101: N | F101: 108205871800 | G101: E31 | H101: 46146 | I101: NL | J101: X | K101: TN | M101: 20260421018 | N101: 870890082009 | R101: 1 | T101: 3PK/20KG | X101: FEDEX
...

Sheet DSKH
A1: DANH SÁCH KHÁCH HÀNG
A2: TÊN | B2: Mã khách hàng | C2: Tên khách hàng | D2: Mã số thuế
A3: AN PHÚ THỊNH | B3: A-01 | C3: CÔNG TY CỔ PHẦN AN PHÚ THỊNH | D3: 3600921992
B4: A-02 | C4: CÔNG TY CỔ PHẦN THIẾT BỊ BÁCH HƯNG | D4: 3603380692
A5: SOVI | B5: A-03 | C5: CÔNG TY CỔ PHẦN BAO BÌ BIÊN HÒA | D5: 3600648493
B6: A-04 | C6: CÔNG TY TNHH BASF VIỆT NAM | D6: 3700238204
A7: CƯỜNG THỊNH | B7: A-05 | C7: CÔNG TY TNHH THƯƠNG MẠI KỸ THUẬT CƯỜNG THỊNH | D7: 3602791481
B8: A-06 | C8: CÔNG TY TNHH ĐẶNG TRUNG QUÂN | D8: 3600953419
A9: HAN BA | B9: A-07 | C9: CÔNG TY TNHH HAN BA | D9: 3600726737
B10: A-08 | C10: CÔNG TY TNHH THƯƠNG MẠI DỊCH VỤ KỸ THUẬT HOẰNG DƯƠNG | D10: 309530820
A11: JAAN-E | B11: A-09 | C11: CÔNG TY TRÁCH NHIỆM HỮU HẠN JAAN-E | D11: 3600813482
A12: KAISER | B12: A-10 | C12: CÔNG TY TNHH KAISER VIỆT NAM | D12: 310176878
B13: A-100 | C13: CÔNG TY TNHH LESCHACO VIỆT NAM | D13: 306573424
B14: A-101 | C14: CÔNG TY TNHH ĐẦU TƯ PHÁT TRIỂN XÂY DỰNG MINH TÂN TIẾN | D14: 3600837797
B15: A-103 | C15: CÔNG TY TNHH CÔNG NGHIỆP PTS | D15: 309999002
B16: A-104 | C16: CÔNG TY TNHH THƯƠNG MẠI THÁI THÀNH | D16: 301379511
B17: A-105 | C17: CÔNG TY TNHH THƯƠNG MẠI NGỌC THIÊM | D17: 3603594158
A18: TRUNG VẠN PHONG | B18: A-689 | C18: CÔNG TY TNHH BÌNH TIÊN ĐỒNG NAI | D18: 3600241531
B19: A-107 | C19: CÔNG TY TNHH RIC CORPORATION LIMITED | D19: 3700886533
B20: A-108 | C20: CÔNG TY TNHH KANGPING TECHNOLOGY (VIỆT NAM) | D20: 3702747084
B21: A-109 | C21: CÔNG TY CỔ PHẦN THAMI SHIPPING & AIRFREIGHT | D21: 303022997
A22: KYC | B22: A-11 | C22: CÔNG TY TNHH MỘT THÀNH VIÊN KYC MACHINE INDUSTRY VIỆT NAM | D22: 3603208839
A23: GĂNG TAY CHU LAI | B23: A-111 | C23: CÔNG TY CỔ PHẦN SẢN XUẤT GĂNG TAY CHU LAI | D23: 4001182818
B24: A-112 | C24: CÔNG TY TNHH SẢN XUẤT THƯƠNG MẠI DỊCH VỤ HUY HOÀNG MINH | D24: 311672678
A25: MATSUYA | B25: A-12 | C25: CÔNG TY TNHH MATSUYA R&D (VIỆT NAM) | D25: 3601000200
B26: A-122 | C26: CÔNG TY CỔ PHẦN THUẬN HIỆP PHÁT | D26: 3602263192
B27: A-123 | C27: CÔNG TY TNHH SẢN XUẤT THƯƠNG MẠI VĨNH PHÁT | D27: 3602313911
B28: A-125 | C28: CÔNG TY TNHH TIN HỌC GIA PHÚC KHANG | D28: 315497191
A29: VÂN LONG CDC | B29: A-128 | C29: CÔNG TY CỔ PHẦN THƯƠNG MẠI ĐẦU TƯ VÂN LONG CDC | D29: 200835768
B30: A-129 | C30: CÔNG TY TNHH SPACE TRADING | D30: 315665872
A31: MẬU DƯƠNG | B31: A-13 | C31: CÔNG TY TNHH MẬU DƯƠNG | D31: 3701671604
B32: A-130 | C32: CÔNG TY TNHH SẢN XUẤT - THƯƠNG MẠI - DỊCH VỤ HOÀNG ĐÔNG | D32: 3600974578
A33: OPTIMA/LYNN | B33: A-131 | C33: CÔNG TY TNHH OPTIMA POWER TOOLS VIỆT NAM | D33: 3603652025
A34: RONGBAOYU | B34: A-132 | C34: CÔNG TY TNHH RONGBAOYU (VIỆT NAM) | D34: 3603680801
B35: A-135 | C35: CÔNG TY TNHH TIẾP VẬN THỰC | D35: 309561064
B36: A-137 | C36: CÔNG TY TNHH HOYER TRANSPORT VIỆT NAM | D36: 310241781
B37: A-138 | C37: CÔNG TY TNHH K&H WALKER SHOES | D37: 3702805836
B38: A-139 | C38: CÔNG TY TNHH LYNN SUPPLY CHAIN (VIETNAM) | D38: 316039860
A39: NEW-TQQT | B39: B-57 | C39: CÔNG TY TNHH NEW VIỆT NAM | D39: 3600545709
B40: A-140 | C40: CÔNG TY TNHH TM - DV P.T & F | D40: 3602580441
B41: A-141 | C41: CÔNG TY CP SADO GERMANY WINDOW | D41: 3602332872
B42: A-142 | C42: CÔNG TY TNHH ANT VINA | D42: 801145335
A43: DAEYEONG/GST | B43: A-143 | C43: CÔNG TY TNHH DAEYEONG VINA | D43: 3603267993
A44: JINGGUANG | B44: A-144 | C44: CÔNG TY TNHH NHỰA JINGGUANG ĐỒNG NAI VIỆT NAM | D44: 3603395427
A45: SUNDAT | B45: A-145 | C45: CÔNG TY TRÁCH NHIỆM HỮU HẠN SUNDAT CROP SCIENCE | D45: 3600744895
B46: A-146 | C46: CÔNG TY CỔ PHẦN THƯƠNG MẠI XUẤT NHẬP KHẨU CO BI CO VINA | D46: 3603651254
B47: A-147 | C47: CÔNG TY HỮU HẠN KỸ THUẬT AXIS STAR VIỆT NAM | D47: 3600793684
B48: A-148 | C48: CÔNG TY CP VĨNH HOÀN | D48: 1400112623
A49: PENFLEX | B49: A-15 | C49: CÔNG TY TNHH PENFLEX VIỆT NAM | D49: 3602314457
B50: A-150 | C50: CÔNG TY CỔ PHẦN GỐM SỨ GRANITE VTC | D50: 3502354336
B51: A-152 | C51: CÔNG TY TNHH IN SMART LABEL | D51: 316113225
B52: A-153 | C52: CÔNG TY TNHH MỘT THÀNH VIÊN THƯƠNG MẠI DỊCH VỤ HOÀNG HUY PHÁT | D52: 3600978759
B53: A-154 | C53: Lê Thanh Hải
B54: A-155 | C54: CÔNG TY TNHH THƯƠNG MẠI GIAO NHẬN VẬN CHUYỂN VÀ TIẾP VẬN THẾ GIỚI MỚI | D54: 305611719
B55: A-157 | C55: CÔNG TY TNHH CHẾ TẠO CÔNG NGHIỆP SÀI GÒN | D55: 3603522636
A56: METROHM | B56: A-158 | C56: CÔNG TY TNHH METROHM VIỆT NAM | D56: 315409597
A57: HAO CHE | B57: A-159 | C57: CÔNG TY TNHH MỘT THÀNH VIÊN HAO CHE | D57: 3603222720
A58: Phú Gia Phát | B58: A-16 | C58: CÔNG TY TNHH BAO BÌ PHÚ GIA PHÁT | D58: 3603064496
A59: tokin - Phú Gia phát | B59: A-16
A60: NEW - Phú Gia phát | B60: A-16
B61: A-160 | C61: CÔNG TY TNHH SẢN XUẤT THƯƠNG MẠI DỊCH VỤ QUANG ĐẠT | D61: 310640257
B62: A-161 | C62: CÔNG TY TNHH NGỌC ĐẠI PHÁT | D62: 3603463765
B63: A-162 | C63: CÔNG TY TNHH DỊCH VỤ TIẾP VẬN TOÀN CẦU | D63: 304995011
B64: A-164 | C64: CÔNG TY TNHH SẢN XUẤT THƯƠNG MẠI DỊCH VỤ XUẤT KHẨU ĐỒ GỖ VẠN KỲ | D64: 3603700705
B65: A-165 | C65: CÔNG TY TNHH CƠ KHÍ MPT | D65: 313009868
B66: A-166 | C66: CÔNG TY TNHH TOLL GLOBAL FORWARDING (VIETNAM) | D66: 311311551
B67: A-167 | C67: CÔNG TY TNHH THƯƠNG MẠI DỊCH VỤ NAM GIANG | D67: 301442146
B68: A-168 | C68: CÔNG TY TNHH TM - DV - VI NA HOÀNG DŨNG | D68: 3600893907
B69: A-169 | C69: CÔNG TY TNHH DỊCH VỤ VẬN TẢI C.H. ROBINSON VIỆT NAM | D69: 1101752826
A70: NHỰA RELIABLE | B70: A-17 | C70: CÔNG TY CỔ PHẦN NHỰA RELIABLE (VIỆT NAM) | D70: 3600507301
B71: A-170 | C71: CÔNG TY CỔ PHẦN THƯƠNG MẠI TIẾP VẬN QUỐC TẾ FTI | D71: 311332304
B72: A-171 | C72: CÔNG TY TNHH VERTICES VIỆT NAM | D72: 314933455
B73: A-172 | C73: CÔNG TY TNHH NAM ĐỒNG TIẾN | D73: 3603697146
B74: A-173 | C74: CÔNG TY TNHH INDOCHINE FOAMTECH | D74: 3702367903
B75: A-174 | C75: CÔNG TY TNHH MỘT THÀNH VIÊN DỊCH VỤ GIAO NHẬN KORNET | D75: 310195581
B76: A-175 | C76: CÔNG TY TNHH MITSUI & CO. GLOBAL LOGISTICS (VIETNAM) | D76: 316000158
B77: A-177 | C77: CÔNG TY CỔ PHẦN ĐẦU TƯ CAMERA VIỆT | D77: 313769996
B78: A-178 | C78: CÔNG TY TNHH CÔNG NGHIỆP VẬT LIỆU GỐM SỨ SHUN YIN | D78: 3600748794
B79: A-179 | C79: CÔNG TY TNHH JASON INDUSTRY VIỆT NAM | D79: 3603630134
A80: RITEK | B80: A-18 | C80: CÔNG TY TRÁCH NHIỆM HỮU HẠN RITEK VIỆT NAM | D80: 3600718951
B81: A-180 | C81: CÔNG TY TNHH BCO LOGISTICS | D81: 316210211
B82: A-181 | C82: CÔNG TY TNHH KUKA SOFA VIỆT NAM | D82: 3603709722
B83: A-182 | C83: CÔNG TY TNHH STAR CONCORD (VIỆT NAM) | D83: 313647412
B84: A-183 | C84: CÔNG TY TNHH THƯƠNG MẠI - DỊCH VỤ - XUẤT NHẬP KHẨU TRM | D84: 316422375
B85: A-184 | C85: CÔNG TY TNHH MỘT BẢY CHÍN VIỆT NAM | D85: 3603571979
A86: 179 FURNITURE | B86: A-184-1 | C86: CÔNG TY TNHH 179 FURNITURE | D86: 3603980160
B87: A-185 | C87: CÔNG TY TNHH THIẾT BỊ XỬ LÝ NƯỚC TOÀN CẦU | D87: 3603498782
A88: KIM HÒA | B88: A-186 | C88: CÔNG TY TNHH THƯƠNG MẠI SẢN XUẤT DỊCH VỤ KIM HÒA | D88: 306025749
B89: A-188 | C89: CÔNG TY TNHH UNIWIN VIỆT NAM | D89: 3603661541
B90: A-189 | C90: CÔNG TY TNHH JASON FURNITURE VIỆT NAM | D90: 3801210244
B91: A-19 | C91: CÔNG TY TNHH SHEN PHAT FURNITURE | D91: 3603057795
B92: A-190 | C92: CÔNG TY LIÊN DOANH TNHH DIMERCO VIETFRACHT | D92: 304199027
B93: A-191 | C93: CÔNG TY TNHH QUỐC TẾ EVER GROWTH (VIỆT NAM) | D93: 3603417984
B94: A-192 | C94: CÔNG TY TNHH THIẾT BỊ VĂN PHÒNG BÌNH PHƯƠNG | D94: 314208513
B95: A-193 | C95: CÔNG TY TNHH THƯƠNG MẠI & HỢP TÁC ĐẦU TƯ NGỌC TRAI VIỆT NAM | D95: 4401034892
A96: ĐẠI LỰC | B96: A-194 | C96: CÔNG TY CỔ PHẦN ĐẠI LỰC ĐỒNG NAI | D96: 3603520420
B97: A-195 | C97: CÔNG TY TNHH THƯƠNG MẠI HẢI MINH | D97: 3600615508
B98: A-196 | C98: CÔNG TY TNHH TƯ VẤN LIBRA | D98: 314619633
A99: CHOONGNAM | B99: A-197 | C99: CÔNG TY DỆT CHOONGNAM VIỆT NAM TRÁCH NHIỆM HỮU HẠN. | D99: 3600248801
B100: A-198 | C100: CÔNG TY TNHH 3D SMART SOLUTIONS | D100: 313566379
...
